MUX.v
`timescale 1ns / 1ps
//////////////////////////////////////////////////////////////////////////////////
// Company: 
// Engineer: 
// 
// Create Date: 03/10/2025 02:27:47 AM
// Design Name: 
// Module Name: MUX
// Project Name: 
// Target Devices: 
// Tool Versions: 
// Description: 
// 
// Dependencies: 
// 
// Revision:
// Revision 0.01 - File Created
// Additional Comments:
// 
//////////////////////////////////////////////////////////////////////////////////


module MUX(
    input wire signal,  // Ensure signal is wire (default for inputs)
    input wire [7:0] mux_in1,
    input wire [7:0] mux_in2,
    output reg [7:0] mux_out // Must be 'reg' since it’s assigned in always block
);

initial begin
    mux_out = 8'b0;
end
always @(*) begin
   case(signal)
       1'b0: mux_out = mux_in1;
       1'b1: mux_out = mux_in2;
   endcase
end

endmodule

AND.v
`timescale 1ns / 1ps
//////////////////////////////////////////////////////////////////////////////////
// Company: 
// Engineer: 
// 
// Create Date: 03/10/2025 03:48:42 AM
// Design Name: 
// Module Name: AND
// Project Name: 
// Target Devices: 
// Tool Versions: 
// Description: 
// 
// Dependencies: 
// 
// Revision:
// Revision 0.01 - File Created
// Additional Comments:
// 
//////////////////////////////////////////////////////////////////////////////////


module AND(
input a,
input b,
output c
    );

assign c = a & b;    

endmodule

data_memory.v
`timescale 1ns / 1ps


module data_memory(
input clk,
input [7:0] read_addr,
input [7:0] write_addr,
input [7:0] write_data,
input mem_write,
input mem_enable,
output reg [7:0] read_data
);

reg [7:0] memory [255:0];
integer i;
reg [7:0] register ;

initial begin
   
    for (i = 0; i < 256; i = i + 1)
        memory[i] = 8'b0000_1001; // Default to 9
end

always @(*) begin
    if (mem_enable)
        if (mem_write) 
            memory[write_addr] <= write_data;
        read_data = memory[read_addr];
        register = memory[read_addr];
    // else 
        // read_data = register;
end



endmodule

ALU.v
`timescale 1ns / 1ps

module ALU(
    input wire [7:0] data_in1,
    input wire [7:0] data_in2,
    input wire [3:0] opcode,
    input wire ALU_src,
    input wire clk,
    output reg [7:0] result,
    output reg compare
);

always @(*) begin
    compare <= 1'b0;
    if (ALU_src) begin
        case (opcode)
            4'b0000: result <= data_in1 + data_in2;   // ADD
            4'b0001: result <= data_in1 - data_in2;   // SUB
            4'b0010: result <= data_in1 & data_in2;   // AND
            4'b0011: result <= data_in1 | data_in2;   // OR
            4'b0100: result <= data_in1 ^ data_in2;   // XOR
            4'b0101: compare <= (data_in1 == data_in2) ? 1'b1 : 1'b0; // COMPARE
            4'b0110: result <= data_in1 + data_in2;   // ADD for load
            4'b0111: result <= data_in1 + data_in2;   // ADD for store
            default: result <= 8'b00000000; // Default case (avoid latches)
        endcase
    end
end

endmodule

Register_file.v
`timescale 1ns / 1ps


module Register_file(
input clk,
input [3:0] read_reg1,
input [3:0] read_reg2,
input [3:0] write_reg,
input [7:0] write_data,
input reg_write,
input reg_enable,
output reg [7:0] read_data1,
output reg [7:0] read_data2
);

reg [7:0] register_memory [15:0];
reg [7:0] register_1;
reg [7:0] register_2;
integer i;
initial begin
   
    for (i = 0; i < 16; i = i + 1)
        register_memory[i] = 16'b0000_0000_0000_0101; // Default to 0
//    register_memory[0] = 16'b0001_0000_0001_0010; 
end

// always @(*) begin
//     if (reg_write | reg_enable) 
//         register_memory[write_reg] <= write_data;
// end



// Read operation
always @(*) begin
    if (reg_enable) begin
        read_data1 = register_memory[read_reg1];
        read_data2 = register_memory[read_reg2];
        register_1 = register_memory[read_reg1];
        register_2 = register_memory[read_reg2];
    end else begin
        read_data1 = register_1;
        read_data2 = register_2;
    end
    if (reg_write & reg_enable) 
        register_memory[write_reg] <= write_data;
end


endmodule

control_unit_multicycle.v
module control_unit_multicycle(
    input wire clk,              // Clock input
    input wire reset,            // Reset signal
    input wire [3:0] opcode,     // Opcode as input
    output reg reg_write,        // Control signal for Register Write
    output reg branch,
    output reg ALU_src,
    output reg load,
    output reg mem_write,
    output reg jump,
    // New control signals for multi-cycle
    output reg PC_enable,        // Enable signal for program counter
    output reg IR_enable,        // Enable signal for instruction register
    // output reg ALU_enable,       // Enable signal for ALU
    output reg mem_enable,       // Enable signal for memory
    output reg reg_enable        // Enable signal for register file
);

// State definitions
localparam FETCH = 2'b00;
localparam DECODE = 2'b01;
localparam EXECUTE = 2'b10;
localparam MEMORY = 2'b11;
localparam WRITEBACK = 3'b100;  // Needs extra bit

reg [2:0] state, next_state;

// State register
always @(posedge clk or posedge reset) begin
    if (reset)
        state <= FETCH;
    else
        state <= next_state;
end

always @(posedge reset) begin
        PC_enable = 1'b1;
end

// Next state logic
always @(*) begin
    case (state)
        FETCH: next_state = DECODE;
        DECODE: next_state = EXECUTE;
        EXECUTE: begin
            if (opcode == 4'b1001 || opcode == 4'b1010)  // Load or Store
                next_state = MEMORY;
            else if (opcode < 7 || opcode == 4'b1001)    // R-type or Load needs writeback
                next_state = WRITEBACK;
            else                                        // Branch or Jump
                next_state = FETCH;
        end
        MEMORY: begin
            if (opcode == 4'b1001)                      // Load needs writeback
                next_state = WRITEBACK;
            else                                        // Store
                next_state = FETCH;
        end
        WRITEBACK: next_state = FETCH;
        default: next_state = FETCH;
    endcase
end

// Output logic
always @(*) begin
    // Default values
    reg_write = 1'b0;
    branch = 1'b0;
    ALU_src = 1'b0;
    load = 1'b0;
    mem_write = 1'b0;
    jump = 1'b0;
    PC_enable = 1'b0;
    IR_enable = 1'b0;
    // ALU_enable = 1'b0;
    mem_enable = 1'b0;
    reg_enable = 1'b0;
    
    case (state)
        FETCH: begin
            IR_enable = 1'b1;    // Enable instruction register
        end
        
        DECODE: begin
            reg_enable = 1'b1;   // Enable register file for reading
        end
        
        EXECUTE: begin
            // ALU_enable = 1'b1;   // Enable ALU
            if (opcode < 7) begin
                ALU_src = 1'b1;  // R-type
            end
            else begin
                case (opcode)
                    4'b0111, 4'b1000: begin  // BEQ, BNE
                        ALU_src = 1'b1;
                        branch = 1'b1;
                        PC_enable = 1'b1;    // Update PC for branch
                    end
                    4'b1001, 4'b1010: begin  // Load/Store
                        ALU_src = 1'b1;
                    end
                    4'b1011: begin          // Jump
                        jump = 1'b1;
                        PC_enable = 1'b1;    // Update PC for jump
                    end
                endcase
            end
        end
        
        MEMORY: begin
            mem_enable = 1'b1;   // Enable memory
            if (opcode == 4'b1001) begin  // Load
                load = 1'b1;
            end
            else if (opcode == 4'b1010) begin  // Store
                mem_write = 1'b1;
                PC_enable = 1'b1;  // Update PC after store completes
            end
        end
        
        WRITEBACK: begin
            reg_enable = 1'b1;    // Enable register file for writing
            reg_write = 1'b1;     // Enable write to register
            PC_enable = 1'b1;     // Update PC after instruction completes
        end
    endcase
end


endmodule

instruction_decoder.v
module instruction_decoder(
    input wire [15:0] instruction,  // Instruction from Instruction Memory
    output reg [3:0] opcode,        // ALU Operation
    output reg [3:0] read_reg1,     // Source Register 1
    output reg [3:0] read_reg2,     // Source Register 2
    output reg [3:0] write_reg,     // Destination Register
    output reg [7:0] immediate      // Immediate Value
);

reg [7:0] extended_value;

always @(*) begin
    opcode    = instruction[15:12]; // Extract opcode (4 bits)
    read_reg1 = instruction[11:8];  // Extract Rs (source register 1)
    read_reg2 = instruction[7:4];   // Extract Rt (source register 2)
    
    if (opcode < 4'b0101) begin // R-type instruction
        write_reg  = instruction[3:0];   // Extract Rd (destination register)
        immediate  = 4'b0000;            // No immediate value in R-type
    end else begin
        
        extended_value = {4'b0000, instruction[3:0]}; // Zero-extend to 8 bits
        
        
        case (opcode)
                    4'b0101: begin // BEQ
                        write_reg  = 4'b0000;            // No destination register in I-type
                        immediate  = extended_value;   // Extract immediate value
                    end
                    4'b0110: begin // LOAD
                        write_reg  = instruction[11:8];            // No destination register in I-type
                        immediate  = extended_value;   // Extract immediate value
                    end
        endcase
    end
end

endmodule

instruction_memory.v
`timescale 1ns / 1ps


module instruction_memory(
input wire [3:0] addr,
output wire [15:0] instruction,
input IR_enable
);

reg [15:0] register_memory [15:0];

assign instruction = register_memory[addr];

integer i;
initial begin
   
    for (i = 0; i < 16; i = i + 1)
        register_memory[i] = 16'b0000_0000_0000_0000; // Default to 0
        //opcode_first_second_destination
        //opcode_first_second_immediate 
        //opcode_first_second_immediate 
    register_memory[1] = 16'b1010_0000_0001_0110; // STORE $r0 6($r1) : r1+6 = r0
    // register_memory[0] = 16'b0000_0000_0001_0110; // ADD
    register_memory[2] = 16'b1001_0101_0001_0110; // LOAD $r0 6($r1) : r0 = r1+6
    // register_memory[1] = 16'b0100_0000_0001_0110; // XNOR
    // register_memory[2] = 16'b0101_0000_1000_0101;  // shift right
    // register_memory[2] = 16'b0000_0110_1000_0111;  // shift right
    register_memory[3] = 16'b0110_0101_1000_0111;  // shift left
    // register_memory[4] = 16'b0111_0000_1111_0010;  // branch if equal   
    register_memory[4] = 16'b1011_0000_0000_0000;  // jump  
    register_memory[5] = 16'b0101_0000_0001_0000;  
    register_memory[6] = 16'b0000_0000_0001_0010;  
    register_memory[7] = 16'b1011_0000_0000_0000; // jump to 0 instruction addr  
end





endmodule

program_counter.v
`timescale 1ns / 1ps

module program_counter(
    input clk,
    input rst,               
    input [7:0] pc_increment, // Lower 4 bits of 8-bit input
    input jump, 
    input PC_enable,
    input [7:0] jump_label,
    output reg [3:0] instruction_addr
);

    reg first_cycle; // Flag to track the first cycle after reset

    // Initialize on reset and handle PC updates
    always @(posedge clk or posedge rst) begin
        if (rst) begin
            instruction_addr <= 4'b0000;   // Reset counter
            first_cycle <= 1'b1;          // Set first cycle flag
        end
        else if (first_cycle || PC_enable) begin
            first_cycle <= 1'b0;          // Clear first cycle flag
            
            if (jump)
                instruction_addr <= jump_label[3:0];  // Jump to address
            else if (pc_increment[3:0] == 4'b0000)
                instruction_addr <= instruction_addr + 4'b0001;  // Increment by 1 when pc_increment is 0
            else
                instruction_addr <= instruction_addr + pc_increment[3:0]; // Increment by pc_increment
        end
        // No else case - if !PC_enable and !first_cycle, PC remains unchanged
    end

endmodule

tb_RISC_16.v
`timescale 1ns / 1ps

module tb_RISC_16;

    // Testbench signals
    reg clk;
    reg rst;
    wire [3:0] instruction_addr;
    wire [15:0] instruction;
    
    wire [3:0] opcode;   // ALU Operation
    wire [3:0] read_reg1; // Source Register 1
    wire [3:0] read_reg2; // Source Register 2
    wire [3:0] write_reg; // Destination Register
    wire [7:0] write_data;
    wire [7:0] read_data1;
    wire [7:0] read_data2;
    wire [7:0] immediate;
    wire compare;
    
    //data memory
    wire [7:0] read_data;
    // wire [7:0] write_addr;
    // wire [7:0] read_data1;
    wire mem_write;
    wire load_signal;
    
    // Control signals
    wire reg_write;        // Control signal for Register Write
    wire ALU_src;
    wire branch;
    wire jump;
    
    wire branch_increment_signal;
    wire [7:0] pc_increment;
    
    wire [7:0] alu_result;
    wire [7:0] read_data1_mux;
    //enable signals
    wire PC_enable;
    wire reg_enable;
    wire IR_enable;
    wire mem_enable;
    
    // Instantiate the 8-bit counter module
    program_counter uut (
        .clk(clk),
        .rst(rst),
        .instruction_addr(instruction_addr),
        .pc_increment(pc_increment),
        .jump(jump),
        .jump_label(immediate),
        .PC_enable(PC_enable)
    );
    
    instruction_memory im(
      .addr(instruction_addr),
      .instruction(instruction),
      .IR_enable(IR_enable)
    );
    
    instruction_decoder id(
    .opcode(opcode),
    .read_reg1(read_reg1),
    .read_reg2(read_reg2),
    .write_reg(write_reg),
    .instruction(instruction),
    .immediate(immediate)
    );
    
    // control_unit cu(
    // .opcode(opcode),
    // .branch(branch),
    // .ALU_src(ALU_src),
    // .reg_write(reg_write),
    // .load(load_signal),
    // .mem_write(mem_write),
    // .jump(jump)
    // );

    control_unit_multicycle cu(
    .reset(rst),
    .clk(clk),
    .opcode(opcode),
    .branch(branch),
    .ALU_src(ALU_src),
    .reg_write(reg_write),
    .load(load_signal),
    .mem_write(mem_write),
    .jump(jump),
    //enable signals 
    .PC_enable(PC_enable),
    .reg_enable(reg_enable),
    .mem_enable(mem_enable),
    .IR_enable(IR_enable)

    );
    
    Register_file rf(
    .read_reg1(read_reg1),
    .read_reg2(read_reg2),
    .write_reg(write_reg),
    .write_data(write_data),
    .read_data1(read_data1),
    .read_data2(read_data2),
    .reg_write(reg_write),
    .reg_enable(reg_enable)
    );
    
    ALU alu(
    .data_in1(read_data1_mux),
    .data_in2(read_data2),
    .opcode(opcode),
    .clk(clk),
    .result(alu_result),
    .ALU_src(ALU_src),
    .compare(compare)
    );
    
    data_memory mm(
    .read_addr(alu_result),
    .write_addr(alu_result),
    .write_data(read_data1),
    .mem_write(mem_write),
    .read_data(read_data),
    .mem_enable(mem_enable)
    );
    
    MUX memory_ALU_mux(
    .signal(load_signal),
    .mux_in2(read_data),
    .mux_in1(alu_result),
    .mux_out(write_data)
    );
    
    AND branch_ALU(
    .a(branch),
    .b(compare),
    .c(branch_increment_signal)
    );
    
     MUX alu_input_selector(
    .signal(load_signal),
    .mux_in2(immediate),
    .mux_in1(read_data1),
    .mux_out(read_data1_mux)
    );
    
    MUX branch_mux(
    .signal(branch_increment_signal),
    .mux_in2(immediate),
    .mux_in1(8'b1),
    .mux_out(pc_increment)
    );
    


    // Clock generation (10ns period -> 100MHz clock)
    always #10 clk = ~clk;

initial begin
    // Enable VCD dumping
    $dumpfile("waveform.vcd");  // Name of the output waveform file
    $dumpvars(0, tb_RISC_16);    // Dump all variables in the module
    clk = 0;
    rst = 0;  
    // PC_enable = 0; // Initialize PC_enable to 0
    #10 rst = 1; // Release reset after 10ns
    #10 rst = 0;
    


    clk = 1'b0;
    // forever begin
    //   #1 clk = ~clk;
    // end

    #10
    clk = ~clk;



    #500;  // Let the simulation run for a longer time
    $finish;  // Stop simulation
end




    // Monitor changes
    initial begin
        $monitor("Time: %0t | clk: %b | rst: %b | pc_increment: %b | instruction_addr: %b | PC_enable: %b | IR_enable: %b | mem_enable: %b | reg_enable: %b", $time, clk, rst, pc_increment, instruction_addr,PC_enable,IR_enable,mem_enable,reg_enable);
    end


//always #5 clk = ~clk; // Toggle clock every 5ns (10ns period)

endmodule

waveform.vcd
$date
	Mon Apr 21 18:30:06 2025
$end
$version
	Icarus Verilog
$end
$timescale
	1ps
$end
$scope module tb_RISC_16 $end
$var wire 4 ! write_reg [3:0] $end
$var wire 8 " write_data [7:0] $end
$var wire 1 # reg_write $end
$var wire 1 $ reg_enable $end
$var wire 4 % read_reg2 [3:0] $end
$var wire 4 & read_reg1 [3:0] $end
$var wire 8 ' read_data2 [7:0] $end
$var wire 8 ( read_data1_mux [7:0] $end
$var wire 8 ) read_data1 [7:0] $end
$var wire 8 * read_data [7:0] $end
$var wire 8 + pc_increment [7:0] $end
$var wire 4 , opcode [3:0] $end
$var wire 1 - mem_write $end
$var wire 1 . mem_enable $end
$var wire 1 / load_signal $end
$var wire 1 0 jump $end
$var wire 4 1 instruction_addr [3:0] $end
$var wire 16 2 instruction [15:0] $end
$var wire 8 3 immediate [7:0] $end
$var wire 1 4 compare $end
$var wire 1 5 branch_increment_signal $end
$var wire 1 6 branch $end
$var wire 8 7 alu_result [7:0] $end
$var wire 1 8 PC_enable $end
$var wire 1 9 IR_enable $end
$var wire 1 : ALU_src $end
$var reg 1 ; clk $end
$var reg 1 < rst $end
$scope module alu $end
$var wire 1 ; clk $end
$var wire 4 = opcode [3:0] $end
$var wire 8 > data_in2 [7:0] $end
$var wire 8 ? data_in1 [7:0] $end
$var wire 1 : ALU_src $end
$var reg 1 4 compare $end
$var reg 8 @ result [7:0] $end
$upscope $end
$scope module alu_input_selector $end
$var wire 1 / signal $end
$var wire 8 A mux_in2 [7:0] $end
$var wire 8 B mux_in1 [7:0] $end
$var reg 8 C mux_out [7:0] $end
$upscope $end
$scope module branch_ALU $end
$var wire 1 4 b $end
$var wire 1 5 c $end
$var wire 1 6 a $end
$upscope $end
$scope module branch_mux $end
$var wire 8 D mux_in1 [7:0] $end
$var wire 1 5 signal $end
$var wire 8 E mux_in2 [7:0] $end
$var reg 8 F mux_out [7:0] $end
$upscope $end
$scope module cu $end
$var wire 1 ; clk $end
$var wire 1 < reset $end
$var wire 4 G opcode [3:0] $end
$var reg 1 : ALU_src $end
$var reg 1 9 IR_enable $end
$var reg 1 8 PC_enable $end
$var reg 1 6 branch $end
$var reg 1 0 jump $end
$var reg 1 / load $end
$var reg 1 . mem_enable $end
$var reg 1 - mem_write $end
$var reg 3 H next_state [2:0] $end
$var reg 1 $ reg_enable $end
$var reg 1 # reg_write $end
$var reg 3 I state [2:0] $end
$upscope $end
$scope module id $end
$var wire 16 J instruction [15:0] $end
$var reg 8 K extended_value [7:0] $end
$var reg 8 L immediate [7:0] $end
$var reg 4 M opcode [3:0] $end
$var reg 4 N read_reg1 [3:0] $end
$var reg 4 O read_reg2 [3:0] $end
$var reg 4 P write_reg [3:0] $end
$upscope $end
$scope module im $end
$var wire 1 9 IR_enable $end
$var wire 16 Q instruction [15:0] $end
$var wire 4 R addr [3:0] $end
$var integer 32 S i [31:0] $end
$upscope $end
$scope module memory_ALU_mux $end
$var wire 8 T mux_in1 [7:0] $end
$var wire 1 / signal $end
$var wire 8 U mux_in2 [7:0] $end
$var reg 8 V mux_out [7:0] $end
$upscope $end
$scope module mm $end
$var wire 1 W clk $end
$var wire 1 . mem_enable $end
$var wire 1 - mem_write $end
$var wire 8 X read_addr [7:0] $end
$var wire 8 Y write_addr [7:0] $end
$var wire 8 Z write_data [7:0] $end
$var reg 8 [ read_data [7:0] $end
$var reg 8 \ register [7:0] $end
$var integer 32 ] i [31:0] $end
$upscope $end
$scope module rf $end
$var wire 1 ^ clk $end
$var wire 4 _ read_reg1 [3:0] $end
$var wire 4 ` read_reg2 [3:0] $end
$var wire 1 $ reg_enable $end
$var wire 1 # reg_write $end
$var wire 8 a write_data [7:0] $end
$var wire 4 b write_reg [3:0] $end
$var reg 8 c read_data1 [7:0] $end
$var reg 8 d read_data2 [7:0] $end
$var reg 8 e register_1 [7:0] $end
$var reg 8 f register_2 [7:0] $end
$var integer 32 g i [31:0] $end
$upscope $end
$scope module uut $end
$var wire 1 8 PC_enable $end
$var wire 1 ; clk $end
$var wire 1 0 jump $end
$var wire 8 h jump_label [7:0] $end
$var wire 8 i pc_increment [7:0] $end
$var wire 1 < rst $end
$var reg 1 j first_cycle $end
$var reg 4 k instruction_addr [3:0] $end
$upscope $end
$upscope $end
$enddefinitions $end
#0
$dumpvars
bx k
xj
b1 i
bx h
b10000 g
bx f
bx e
bx d
bx c
bx b
b0 a
bx `
bx _
z^
b100000000 ]
bx \
bx [
bx Z
bx Y
bx X
zW
b0 V
bx U
bx T
b10000 S
bx R
bx Q
bx P
bx O
bx N
bx M
bx L
bx K
bx J
bx I
bx H
bx G
b1 F
bx E
b1 D
b0 C
bx B
bx A
bx @
b0 ?
bx >
bx =
0<
0;
x:
x9
x8
bx 7
x6
05
04
bx 3
bx 2
bx 1
x0
x/
x.
x-
bx ,
b1 +
bx *
bx )
b0 (
bx '
bx &
bx %
x$
x#
b0 "
bx !
$end
#10000
bx (
bx ?
bx C
bx "
bx V
bx a
b0 3
b0 A
b0 E
b0 L
b0 h
b0 !
b0 P
b0 b
b0 %
b0 O
b0 `
b0 &
b0 N
b0 _
b0 ,
b0 =
b0 G
b0 M
0$
0.
19
00
0-
0/
0:
06
0#
b1 H
1j
b0 2
b0 J
b0 Q
b0 1
b0 R
b0 k
b0 I
08
1<
1;
#20000
0<
0;
#30000
b101 (
b101 ?
b101 C
b101 f
b101 e
b101 '
b101 >
b101 d
b101 )
b101 B
b101 Z
b101 c
1$
09
b10 H
b110 3
b110 A
b110 E
b110 L
b110 h
b110 K
b1 %
b1 O
b1 `
b1010 ,
b1010 =
b1010 G
b1010 M
b1 I
b1010000000010110 2
b1010000000010110 J
b1010000000010110 Q
b1 1
b1 R
b1 k
0j
0;
#40000
b1010 "
b1010 V
b1010 a
b1001 \
b1001 *
b1001 U
b1001 [
b1010 7
b1010 @
b1010 T
b1010 X
b1010 Y
b11 H
1:
0$
b10 I
1;
#50000
0;
#60000
b101 \
b101 *
b101 U
b101 [
18
1-
1.
0:
b0 H
b11 I
1;
#70000
0;
#80000
b101 !
b101 P
b101 b
b101 &
b101 N
b101 _
b1001 ,
b1001 =
b1001 G
b1001 M
b1 H
19
0.
08
0-
b1001010100010110 2
b1001010100010110 J
b1001010100010110 Q
b10 1
b10 R
b10 k
b0 I
1;
#90000
0;
#100000
b10 H
1$
09
b1 I
1;
#110000
0;
#120000
1:
0$
b11 H
b10 I
1;
#130000
0;
#140000
b110 (
b110 ?
b110 C
b101 "
b101 V
b101 a
b100 H
1/
1.
0:
b11 I
1;
#150000
0;
#160000
b1010 e
b1010 )
b1010 B
b1010 Z
b1010 c
b1010 (
b1010 ?
b1010 C
b1010 "
b1010 V
b1010 a
18
1#
1$
0.
0/
b0 H
b100 I
1;
#170000
0;
#180000
b1 H
19
0$
08
0#
b0 3
b0 A
b0 E
b0 L
b0 h
b111 !
b111 P
b111 b
b1000 %
b1000 O
b1000 `
b110 ,
b110 =
b110 G
b110 M
b0 I
b110010110000111 2
b110010110000111 J
b110010110000111 Q
b11 1
b11 R
b11 k
1;
#190000
0;
#200000
1$
09
b10 H
b1 I
1;
#210000
0;
#220000
b1000000 "
b1000000 V
b1000000 a
b1001 \
b1001 *
b1001 U
b1001 [
b1000000 7
b1000000 @
b1000000 T
b1000000 X
b1000000 Y
b100 H
1:
0$
b10 I
1;
#230000
0;
#240000
18
1#
1$
0:
b0 H
b100 I
1;
#250000
0;
#260000
b1 H
19
0$
08
0#
b0 !
b0 P
b0 b
b0 K
b0 %
b0 O
b0 `
b0 &
b0 N
b0 _
b1011 ,
b1011 =
b1011 G
b1011 M
b0 I
b1011000000000000 2
b1011000000000000 J
b1011000000000000 Q
b100 1
b100 R
b100 k
1;
#270000
0;
#280000
b101 (
b101 ?
b101 C
b101 e
b101 )
b101 B
b101 Z
b101 c
1$
09
b10 H
b1 I
1;
#290000
0;
#300000
b0 H
18
10
0$
b10 I
1;
#310000
0;
#320000
b0 ,
b0 =
b0 G
b0 M
19
08
00
b1 H
b0 2
b0 J
b0 Q
b0 1
b0 R
b0 k
b0 I
1;
#330000
0;
#340000
1$
09
b10 H
b1 I
1;
#350000
0;
#360000
b1010 "
b1010 V
b1010 a
b101 \
b101 *
b101 U
b101 [
b1010 7
b1010 @
b1010 T
b1010 X
b1010 Y
b100 H
1:
0$
b10 I
1;
#370000
0;
#380000
b1010 (
b1010 ?
b1010 C
b1010 f
b1010 e
b1010 '
b1010 >
b1010 d
b1010 )
b1010 B
b1010 Z
b1010 c
18
1#
1$
0:
b0 H
b100 I
1;
#390000
0;
#400000
b110 3
b110 A
b110 E
b110 L
b110 h
b110 K
b1 %
b1 O
b1 `
b1010 ,
b1010 =
b1010 G
b1010 M
b1 H
19
0$
08
0#
b1010000000010110 2
b1010000000010110 J
b1010000000010110 Q
b1 1
b1 R
b1 k
b0 I
1;
#410000
0;
#420000
b101 f
b101 '
b101 >
b101 d
b10 H
1$
09
b1 I
1;
#430000
0;
#440000
b1111 "
b1111 V
b1111 a
b1001 \
b1001 *
b1001 U
b1001 [
b1111 7
b1111 @
b1111 T
b1111 X
b1111 Y
1:
0$
b11 H
b10 I
1;
#450000
0;
#460000
b1010 \
b1010 *
b1010 U
b1010 [
b0 H
18
1-
1.
0:
b11 I
1;
#470000
0;
#480000
b101 !
b101 P
b101 b
b101 &
b101 N
b101 _
b1001 ,
b1001 =
b1001 G
b1001 M
19
0.
08
0-
b1 H
b1001010100010110 2
b1001010100010110 J
b1001010100010110 Q
b10 1
b10 R
b10 k
b0 I
1;
#490000
0;
#500000
1$
09
b10 H
b1 I
1;
#510000
0;
#520000
b11 H
1:
0$
b10 I
1;
