MUX.v
`timescale 1ns / 1ps
//////////////////////////////////////////////////////////////////////////////////
// Company: 
// Engineer: 
// 
// Create Date: 03/10/2025 02:27:47 AM
// Design Name: 
// Module Name: MUX
// Project Name: 
// Target Devices: 
// Tool Versions: 
// Description: 
// 
// Dependencies: 
// 
// Revision:
// Revision 0.01 - File Created
// Additional Comments:
// 
//////////////////////////////////////////////////////////////////////////////////


module MUX(
    input wire signal,  // Ensure signal is wire (default for inputs)
    input wire [7:0] mux_in1,
    input wire [7:0] mux_in2,
    output reg [7:0] mux_out // Must be 'reg' since it’s assigned in always block
);

initial begin
    mux_out = 8'b0;
end
always @(*) begin
   case(signal)
       1'b0: mux_out = mux_in1;
       1'b1: mux_out = mux_in2;
   endcase
end

endmodule

AND.v
`timescale 1ns / 1ps
//////////////////////////////////////////////////////////////////////////////////
// Company: 
// Engineer: 
// 
// Create Date: 03/10/2025 03:48:42 AM
// Design Name: 
// Module Name: AND
// Project Name: 
// Target Devices: 
// Tool Versions: 
// Description: 
// 
// Dependencies: 
// 
// Revision:
// Revision 0.01 - File Created
// Additional Comments:
// 
//////////////////////////////////////////////////////////////////////////////////


module AND(
input a,
input b,
output c
    );

assign c = a & b;    

endmodule

data_memory.v
`timescale 1ns / 1ps


module data_memory(
input clk,
input [7:0] read_addr,
input [7:0] write_addr,
input [7:0] write_data,
input mem_write,
output reg [7:0] read_data
);

reg [7:0] memory [255:0];
integer i;
initial begin
   
    for (i = 0; i < 256; i = i + 1)
        memory[i] = 8'b0000_1001; // Default to 9
end

always @(*) begin

    if (mem_write) 
        memory[write_addr] <= write_data;
    read_data = memory[read_addr];
end



endmodule

ALU.v
`timescale 1ns / 1ps

module ALU(
    input wire [7:0] data_in1,
    input wire [7:0] data_in2,
    input wire [3:0] opcode,
    input wire ALU_src,
    input wire clk,
    output reg [7:0] result,
    output reg compare
);

always @(*) begin
    compare <= 1'b0;
    if (ALU_src) begin
        case (opcode)
            4'b0000: result <= data_in1 + data_in2;   // ADD
            4'b0001: result <= data_in1 - data_in2;   // SUB
            4'b0010: result <= data_in1 & data_in2;   // AND
            4'b0011: result <= data_in1 | data_in2;   // OR
            4'b0100: result <= data_in1 ^ data_in2;   // XOR
            4'b0101: compare <= (data_in1 == data_in2) ? 1'b1 : 1'b0; // COMPARE
            4'b0110: result <= data_in1 + data_in2;   // ADD for load
            4'b0111: result <= data_in1 + data_in2;   // ADD for store
            default: result <= 8'b00000000; // Default case (avoid latches)
        endcase
    end
end

endmodule

Register_file.v
`timescale 1ns / 1ps


module Register_file(
input clk,
input [3:0] read_reg1,
input [3:0] read_reg2,
input [3:0] write_reg,
input [7:0] write_data,
input reg_write,
output reg [7:0] read_data1,
output reg [7:0] read_data2
);

reg [7:0] register_memory [15:0];
integer i;
initial begin
   
    for (i = 0; i < 16; i = i + 1)
        register_memory[i] = 16'b0000_0000_0000_0101; // Default to 0
//    register_memory[0] = 16'b0001_0000_0001_0010; 
end

always @(*) begin
    if (reg_write) 
        register_memory[write_reg] <= write_data;
end

always @(*) begin
    read_data1 = register_memory[read_reg1];
    read_data2 = register_memory[read_reg2];
end


endmodule

control_unit.v
`timescale 1ns / 1ps
//////////////////////////////////////////////////////////////////////////////////
// Company: 
// Engineer: 
// 
// Create Date: 03/03/2025 10:57:49 PM
// Design Name: 
// Module Name: control_unit
// Project Name: 
// Target Devices: 
// Tool Versions: 
// Description: 
// 
// Dependencies: 
// 
// Revision:
// Revision 0.01 - File Created
// Additional Comments:
// 
//////////////////////////////////////////////////////////////////////////////////

module control_unit(
    input wire [3:0] opcode,     // Opcode as input
    output reg reg_write,        // Control signal for Register Write
    output reg branch,
    output reg ALU_src,
    output reg load,
    output reg mem_write
);

initial begin
reg_write = 1'b0;
branch = 1'b0;
ALU_src = 1'b0;
load = 1'b0;
mem_write = 1'b0;
end
always @(*) begin
reg_write = 1'b0;
branch = 1'b0;
ALU_src = 1'b0;
load = 1'b0;
mem_write = 1'b0;

if (opcode < 5) begin 
    // R-type instruction execution 
    reg_write = 1'b1;
    ALU_src = 1'b1;
end
else begin
    case (opcode)
        4'b0101: begin // branch if equal BNE
            ALU_src = 1'b1;
            branch = 1'b1;
        end
        4'b0110: begin // load instruction
            ALU_src = 1'b1;
            load = 1'b1;
            reg_write = 1'b1;
        end
        4'b0111: begin // store instruction 
            ALU_src = 1'b1;
            load = 1'b1;
            mem_write = 1'b1;
        end
    endcase
end
    
    

    
end

endmodule

instruction_decoder.v
module instruction_decoder(
    input wire [15:0] instruction,  // Instruction from Instruction Memory
    output reg [3:0] opcode,        // ALU Operation
    output reg [3:0] read_reg1,     // Source Register 1
    output reg [3:0] read_reg2,     // Source Register 2
    output reg [3:0] write_reg,     // Destination Register
    output reg [7:0] immediate      // Immediate Value
);

reg [7:0] extended_value;

always @(*) begin
    opcode    = instruction[15:12]; // Extract opcode (4 bits)
    read_reg1 = instruction[11:8];  // Extract Rs (source register 1)
    read_reg2 = instruction[7:4];   // Extract Rt (source register 2)
    
    if (opcode < 4'b0101) begin // R-type instruction
        write_reg  = instruction[3:0];   // Extract Rd (destination register)
        immediate  = 4'b0000;            // No immediate value in R-type
    end else begin
        
        extended_value = {4'b0000, instruction[3:0]}; // Zero-extend to 8 bits
        
        
        case (opcode)
                    4'b0101: begin // BEQ
                        write_reg  = 4'b0000;            // No destination register in I-type
                        immediate  = extended_value;   // Extract immediate value
                    end
                    4'b0110: begin // LOAD
                        write_reg  = instruction[11:8];            // No destination register in I-type
                        immediate  = extended_value;   // Extract immediate value
                    end
                    4'b0111: begin // STORE
                        write_reg  = instruction[11:8];            // No destination register in I-type
                        immediate  = extended_value;   // Extract immediate value
                    end
        endcase
    end
end

endmodule

instruction_memory.v
`timescale 1ns / 1ps


module instruction_memory(
input wire [3:0] addr,
output wire [15:0] instruction
);

reg [15:0] register_memory [15:0];

assign instruction = register_memory[addr];

integer i;
initial begin
   
    for (i = 0; i < 16; i = i + 1)
        register_memory[i] = 16'b0000_0000_0000_0000; // Default to 0
        //opcode_first_second_destination
        //opcode_first_second_immediate 
        //opcode_first_second_immediate 
    register_memory[0] = 16'b0111_0000_0001_0110; // STORE $r0 6($r1) : r1+6 = r0
    register_memory[1] = 16'b0110_0101_0001_0110; // LOAD $r0 6($r1) : r0 = r1+6
    register_memory[2] = 16'b0001_0000_0100_0101;  
    register_memory[3] = 16'b0110_0000_0101_0111;  
    register_memory[4] = 16'b0001_0000_1100_1011;  
    register_memory[5] = 16'b0101_0000_0001_0000;  
    register_memory[6] = 16'b0101_0000_0001_0010;  
    register_memory[7] = 16'b0011_0100_1100_1011;  
end





endmodule

program_counter.v
`timescale 1ns / 1ps

module program_counter(
    input clk,
    input rst,               
    input [7:0] pc_increment, // Lower 4 bits of 8-bit input
    output reg [3:0] instruction_addr
);

    always @(posedge clk or posedge rst) begin
        if (rst)
            instruction_addr <= 4'b0000;   // Reset counter
        else if (pc_increment[3:0] == 4'b0000)
            instruction_addr <= instruction_addr + 4'b0001;  // Increment by 1 when pc_increment is 0
        else
            instruction_addr <= instruction_addr + pc_increment[3:0]; // Normal increment
    end

endmodule

tb_RISC_16.v
`timescale 1ns / 1ps

module tb_RISC_16;

    // Testbench signals
    reg clk;
    reg rst;
    wire [3:0] instruction_addr;
    wire [15:0] instruction;
    
    wire [3:0] opcode;   // ALU Operation
    wire [3:0] read_reg1; // Source Register 1
    wire [3:0] read_reg2; // Source Register 2
    wire [3:0] write_reg; // Destination Register
    wire [7:0] write_data;
    wire [7:0] read_data1;
    wire [7:0] read_data2;
    wire [7:0] immediate;
    wire compare;
    
    //data memory
    wire [7:0] read_data;
    // wire [7:0] write_addr;
    // wire [7:0] read_data1;
    wire mem_write;
    wire load_signal;
    
    // Control signals
    wire reg_write;        // Control signal for Register Write
    wire ALU_src;
    wire branch;
    
    wire branch_increment_signal;
    wire [7:0] pc_increment;
    
    wire [7:0] alu_result;
    wire [7:0] read_data1_mux;
    
    // Instantiate the 8-bit counter module
    program_counter uut (
        .clk(clk),
        .rst(rst),
        .instruction_addr(instruction_addr),
        .pc_increment(pc_increment)
    );
    
    instruction_memory im(
      .addr(instruction_addr),
      .instruction(instruction)
    );
    
    instruction_decoder id(
    .opcode(opcode),
    .read_reg1(read_reg1),
    .read_reg2(read_reg2),
    .write_reg(write_reg),
    .instruction(instruction),
    .immediate(immediate)
    );
    
    control_unit cu(
    .opcode(opcode),
    .branch(branch),
    .ALU_src(ALU_src),
    .reg_write(reg_write),
    .load(load_signal),
    .mem_write(mem_write)
    );
    
    Register_file rf(
    .read_reg1(read_reg1),
    .read_reg2(read_reg2),
    .write_reg(write_reg),
    .write_data(write_data),
    .read_data1(read_data1),
    .read_data2(read_data2),
    .reg_write(reg_write)
    );
    
    ALU alu(
    .data_in1(read_data1_mux),
    .data_in2(read_data2),
    .opcode(opcode),
    .clk(clk),
    .result(alu_result),
    .ALU_src(ALU_src),
    .compare(compare)
    );
    
    data_memory mm(
    .read_addr(alu_result),
    .write_addr(alu_result),
    .write_data(read_data1),
    .mem_write(mem_write),
    .read_data(read_data)
    );
    
    MUX memory_ALU_mux(
    .signal(load_signal),
    .mux_in2(read_data),
    .mux_in1(alu_result),
    .mux_out(write_data)
    );
    
    AND branch_ALU(
    .a(branch),
    .b(compare),
    .c(branch_increment_signal)
    );
    
     MUX alu_input_selector(
    .signal(load_signal),
    .mux_in2(immediate),
    .mux_in1(read_data1),
    .mux_out(read_data1_mux)
    );
    
    MUX branch_mux(
    .signal(branch_increment_signal),
    .mux_in2(immediate),
    .mux_in1(8'b1),
    .mux_out(pc_increment)
    );
    


    // Clock generation (10ns period -> 100MHz clock)
    always #10 clk = ~clk;

initial begin
    // Enable VCD dumping
    $dumpfile("waveform.vcd");  // Name of the output waveform file
    $dumpvars(0, tb_RISC_16);    // Dump all variables in the module
    clk = 0;
    rst = 0;  
    #10 rst = 1; // Release reset after 10ns
    #10 rst = 0;
    


    clk = 1'b0;
    // forever begin
    //   #1 clk = ~clk;
    // end

    #10
    clk = ~clk;
    // #10
    // clk = ~clk;
    // #10
    // clk = ~clk;
    // #10
    // clk = ~clk;
    // #10
    // clk = ~clk;
    // #10
    // clk = ~clk;
    // #10
    // clk = ~clk;



    #500;  // Let the simulation run for a longer time
    $finish;  // Stop simulation
end


 // Clock generation
    // always #5 clk = ~clk; // 10ns period (5ns high, 5ns low)

    // initial begin
    //     // Initialize signals
    //      $dumpfile("waveform.vcd");  // Name of the output waveform file
    //     clk = 0;
    //     rst = 1;
    //     // pc_increment = 4'b0010; // Increment by 2
    //     clk = 1;
        
    //     #10 rst = 0;  // Release reset after 10ns
    //     #600 $finish; // Run simulation for 600ns
    // end

    // Monitor changes
    initial begin
        $monitor("Time: %0t | clk: %b | rst: %b | pc_increment: %b | instruction_addr: %b", $time, clk, rst, pc_increment, instruction_addr);
    end


//always #5 clk = ~clk; // Toggle clock every 5ns (10ns period)

endmodule

waveform.vcd
$date
	Wed Mar 19 17:55:33 2025
$end
$version
	Icarus Verilog
$end
$timescale
	1ps
$end
$scope module tb_RISC_16 $end
$var wire 4 ! write_reg [3:0] $end
$var wire 8 " write_data [7:0] $end
$var wire 1 # reg_write $end
$var wire 4 $ read_reg2 [3:0] $end
$var wire 4 % read_reg1 [3:0] $end
$var wire 8 & read_data2 [7:0] $end
$var wire 8 ' read_data1_mux [7:0] $end
$var wire 8 ( read_data1 [7:0] $end
$var wire 8 ) read_data [7:0] $end
$var wire 8 * pc_increment [7:0] $end
$var wire 4 + opcode [3:0] $end
$var wire 1 , mem_write $end
$var wire 1 - load_signal $end
$var wire 4 . instruction_addr [3:0] $end
$var wire 16 / instruction [15:0] $end
$var wire 8 0 immediate [7:0] $end
$var wire 1 1 compare $end
$var wire 1 2 branch_increment_signal $end
$var wire 1 3 branch $end
$var wire 8 4 alu_result [7:0] $end
$var wire 1 5 ALU_src $end
$var reg 1 6 clk $end
$var reg 1 7 rst $end
$scope module alu $end
$var wire 1 6 clk $end
$var wire 4 8 opcode [3:0] $end
$var wire 8 9 data_in2 [7:0] $end
$var wire 8 : data_in1 [7:0] $end
$var wire 1 5 ALU_src $end
$var reg 1 1 compare $end
$var reg 8 ; result [7:0] $end
$upscope $end
$scope module alu_input_selector $end
$var wire 1 - signal $end
$var wire 8 < mux_in2 [7:0] $end
$var wire 8 = mux_in1 [7:0] $end
$var reg 8 > mux_out [7:0] $end
$upscope $end
$scope module branch_ALU $end
$var wire 1 1 b $end
$var wire 1 2 c $end
$var wire 1 3 a $end
$upscope $end
$scope module branch_mux $end
$var wire 8 ? mux_in1 [7:0] $end
$var wire 1 2 signal $end
$var wire 8 @ mux_in2 [7:0] $end
$var reg 8 A mux_out [7:0] $end
$upscope $end
$scope module cu $end
$var wire 4 B opcode [3:0] $end
$var reg 1 5 ALU_src $end
$var reg 1 3 branch $end
$var reg 1 - load $end
$var reg 1 , mem_write $end
$var reg 1 # reg_write $end
$upscope $end
$scope module id $end
$var wire 16 C instruction [15:0] $end
$var reg 8 D extended_value [7:0] $end
$var reg 8 E immediate [7:0] $end
$var reg 4 F opcode [3:0] $end
$var reg 4 G read_reg1 [3:0] $end
$var reg 4 H read_reg2 [3:0] $end
$var reg 4 I write_reg [3:0] $end
$upscope $end
$scope module im $end
$var wire 16 J instruction [15:0] $end
$var wire 4 K addr [3:0] $end
$var integer 32 L i [31:0] $end
$upscope $end
$scope module memory_ALU_mux $end
$var wire 8 M mux_in1 [7:0] $end
$var wire 1 - signal $end
$var wire 8 N mux_in2 [7:0] $end
$var reg 8 O mux_out [7:0] $end
$upscope $end
$scope module mm $end
$var wire 1 P clk $end
$var wire 1 , mem_write $end
$var wire 8 Q read_addr [7:0] $end
$var wire 8 R write_addr [7:0] $end
$var wire 8 S write_data [7:0] $end
$var reg 8 T read_data [7:0] $end
$var integer 32 U i [31:0] $end
$upscope $end
$scope module rf $end
$var wire 1 V clk $end
$var wire 4 W read_reg1 [3:0] $end
$var wire 4 X read_reg2 [3:0] $end
$var wire 1 # reg_write $end
$var wire 8 Y write_data [7:0] $end
$var wire 4 Z write_reg [3:0] $end
$var reg 8 [ read_data1 [7:0] $end
$var reg 8 \ read_data2 [7:0] $end
$var integer 32 ] i [31:0] $end
$upscope $end
$scope module uut $end
$var wire 1 6 clk $end
$var wire 8 ^ pc_increment [7:0] $end
$var wire 1 7 rst $end
$var reg 4 _ instruction_addr [3:0] $end
$upscope $end
$upscope $end
$enddefinitions $end
#0
$dumpvars
bx _
b1 ^
b10000 ]
bx \
bx [
bx Z
bx Y
bx X
bx W
zV
b100000000 U
bx T
bx S
bx R
bx Q
zP
bx O
bx N
bx M
b10000 L
bx K
bx J
bx I
bx H
bx G
bx F
bx E
bx D
bx C
bx B
b1 A
bx @
b1 ?
bx >
bx =
bx <
bx ;
bx :
bx 9
bx 8
07
06
05
bx 4
03
02
01
bx 0
bx /
bx .
0-
0,
bx +
b1 *
bx )
bx (
bx '
bx &
bx %
bx $
0#
bx "
bx !
$end
#10000
b101 "
b101 O
b101 Y
b101 )
b101 N
b101 T
b1011 4
b1011 ;
b1011 M
b1011 Q
b1011 R
b110 '
b110 :
b110 >
b101 &
b101 9
b101 \
b101 (
b101 =
b101 S
b101 [
1,
1-
15
b110 0
b110 <
b110 @
b110 E
b0 !
b0 I
b0 Z
b110 D
b1 $
b1 H
b1 X
b0 %
b0 G
b0 W
b111 +
b111 8
b111 B
b111 F
b111000000010110 /
b111000000010110 C
b111000000010110 J
b0 .
b0 K
b0 _
17
16
#20000
07
06
#30000
1#
0,
1-
15
b101 !
b101 I
b101 Z
b101 %
b101 G
b101 W
b110 +
b110 8
b110 B
b110 F
b110010100010110 /
b110010100010110 C
b110010100010110 J
b1 .
b1 K
b1 _
06
#40000
b1001 (
b1001 =
b1001 S
b1001 [
b1001 "
b1001 O
b1001 Y
b1001 )
b1001 N
b1001 T
b1010 4
b1010 ;
b1010 M
b1010 Q
b1010 R
b101 '
b101 :
b101 >
b101 0
b101 <
b101 @
b101 E
b0 !
b0 I
b0 Z
b101 D
b100 $
b100 H
b100 X
b0 %
b0 G
b0 W
b110000001000101 /
b110000001000101 C
b110000001000101 J
b10 .
b10 K
b10 _
16
#50000
06
#60000
b1100 4
b1100 ;
b1100 M
b1100 Q
b1100 R
b111 '
b111 :
b111 >
b111 0
b111 <
b111 @
b111 E
b111 D
b101 $
b101 H
b101 X
b110000001010111 /
b110000001010111 C
b110000001010111 J
b11 .
b11 K
b11 _
16
#70000
06
#80000
b100 4
b100 ;
b100 M
b100 Q
b100 R
b100 "
b100 O
b100 Y
b1001 '
b1001 :
b1001 >
0-
15
1#
b0 0
b0 <
b0 @
b0 E
b1011 !
b1011 I
b1011 Z
b1100 $
b1100 H
b1100 X
b1 +
b1 8
b1 B
b1 F
b1000011001011 /
b1000011001011 C
b1000011001011 J
b100 .
b100 K
b100 _
16
#90000
06
#100000
13
15
0#
b0 !
b0 I
b0 Z
b0 D
b1 $
b1 H
b1 X
b101 +
b101 8
b101 B
b101 F
b101000000010000 /
b101000000010000 C
b101000000010000 J
b101 .
b101 K
b101 _
16
#110000
06
#120000
b10 0
b10 <
b10 @
b10 E
b10 D
b101000000010010 /
b101000000010010 C
b101000000010010 J
b110 .
b110 K
b110 _
16
#130000
06
#140000
b101 "
b101 O
b101 Y
b101 4
b101 ;
b101 M
b101 Q
b101 R
b101 '
b101 :
b101 >
b101 (
b101 =
b101 S
b101 [
1#
15
03
b0 0
b0 <
b0 @
b0 E
b1011 !
b1011 I
b1011 Z
b1100 $
b1100 H
b1100 X
b100 %
b100 G
b100 W
b11 +
b11 8
b11 B
b11 F
b11010011001011 /
b11010011001011 C
b11010011001011 J
b111 .
b111 K
b111 _
16
#150000
06
#160000
b0 "
b0 O
b0 Y
b0 4
b0 ;
b0 M
b0 Q
b0 R
b0 '
b0 :
b0 >
b0 &
b0 9
b0 \
b0 (
b0 =
b0 S
b0 [
15
1#
b0 !
b0 I
b0 Z
b0 $
b0 H
b0 X
b0 %
b0 G
b0 W
b0 +
b0 8
b0 B
b0 F
b0 /
b0 C
b0 J
b1000 .
b1000 K
b1000 _
16
#170000
06
#180000
b1001 .
b1001 K
b1001 _
16
#190000
06
#200000
b1010 .
b1010 K
b1010 _
16
#210000
06
#220000
b1011 .
b1011 K
b1011 _
16
#230000
06
#240000
b1100 .
b1100 K
b1100 _
16
#250000
06
#260000
b1101 .
b1101 K
b1101 _
16
#270000
06
#280000
b1110 .
b1110 K
b1110 _
16
#290000
06
#300000
b1111 .
b1111 K
b1111 _
16
#310000
06
#320000
b0 )
b0 N
b0 T
b1011 4
b1011 ;
b1011 M
b1011 Q
b1011 R
b0 "
b0 O
b0 Y
b110 '
b110 :
b110 >
b101 &
b101 9
b101 \
1,
1-
15
0#
b110 0
b110 <
b110 @
b110 E
b110 D
b1 $
b1 H
b1 X
b111 +
b111 8
b111 B
b111 F
b111000000010110 /
b111000000010110 C
b111000000010110 J
b0 .
b0 K
b0 _
16
#330000
06
#340000
b0 (
b0 =
b0 S
b0 [
1#
0,
1-
15
b101 !
b101 I
b101 Z
b101 %
b101 G
b101 W
b110 +
b110 8
b110 B
b110 F
b110010100010110 /
b110010100010110 C
b110010100010110 J
b1 .
b1 K
b1 _
16
#350000
06
#360000
b1001 (
b1001 =
b1001 S
b1001 [
b1001 "
b1001 O
b1001 Y
b1001 )
b1001 N
b1001 T
b1010 4
b1010 ;
b1010 M
b1010 Q
b1010 R
b101 '
b101 :
b101 >
b101 0
b101 <
b101 @
b101 E
b0 !
b0 I
b0 Z
b101 D
b100 $
b100 H
b100 X
b0 %
b0 G
b0 W
b110000001000101 /
b110000001000101 C
b110000001000101 J
b10 .
b10 K
b10 _
16
#370000
06
#380000
b111 4
b111 ;
b111 M
b111 Q
b111 R
b111 '
b111 :
b111 >
b0 &
b0 9
b0 \
b111 0
b111 <
b111 @
b111 E
b111 D
b101 $
b101 H
b101 X
b110000001010111 /
b110000001010111 C
b110000001010111 J
b11 .
b11 K
b11 _
16
#390000
06
#400000
b100 4
b100 ;
b100 M
b100 Q
b100 R
b100 "
b100 O
b100 Y
b1001 '
b1001 :
b1001 >
b101 &
b101 9
b101 \
0-
15
1#
b0 0
b0 <
b0 @
b0 E
b1011 !
b1011 I
b1011 Z
b1100 $
b1100 H
b1100 X
b1 +
b1 8
b1 B
b1 F
b1000011001011 /
b1000011001011 C
b1000011001011 J
b100 .
b100 K
b100 _
16
#410000
06
#420000
13
15
0#
b0 !
b0 I
b0 Z
b0 D
b1 $
b1 H
b1 X
b101 +
b101 8
b101 B
b101 F
b101000000010000 /
b101000000010000 C
b101000000010000 J
b101 .
b101 K
b101 _
16
#430000
06
#440000
b10 0
b10 <
b10 @
b10 E
b10 D
b101000000010010 /
b101000000010010 C
b101000000010010 J
b110 .
b110 K
b110 _
16
#450000
06
#460000
b101 "
b101 O
b101 Y
b101 4
b101 ;
b101 M
b101 Q
b101 R
b101 '
b101 :
b101 >
b101 (
b101 =
b101 S
b101 [
1#
15
03
b0 0
b0 <
b0 @
b0 E
b1011 !
b1011 I
b1011 Z
b1100 $
b1100 H
b1100 X
b100 %
b100 G
b100 W
b11 +
b11 8
b11 B
b11 F
b11010011001011 /
b11010011001011 C
b11010011001011 J
b111 .
b111 K
b111 _
16
#470000
06
#480000
b0 )
b0 N
b0 T
b0 "
b0 O
b0 Y
b0 4
b0 ;
b0 M
b0 Q
b0 R
b0 '
b0 :
b0 >
b0 &
b0 9
b0 \
b0 (
b0 =
b0 S
b0 [
15
1#
b0 !
b0 I
b0 Z
b0 $
b0 H
b0 X
b0 %
b0 G
b0 W
b0 +
b0 8
b0 B
b0 F
b0 /
b0 C
b0 J
b1000 .
b1000 K
b1000 _
16
#490000
06
#500000
b1001 .
b1001 K
b1001 _
16
#510000
06
#520000
b1010 .
b1010 K
b1010 _
16
