MUX.v
`timescale 1ns / 1ps
//////////////////////////////////////////////////////////////////////////////////
// Company: 
// Engineer: 
// 
// Create Date: 03/10/2025 02:27:47 AM
// Design Name: 
// Module Name: MUX
// Project Name: 
// Target Devices: 
// Tool Versions: 
// Description: 
// 
// Dependencies: 
// 
// Revision:
// Revision 0.01 - File Created
// Additional Comments:
// 
//////////////////////////////////////////////////////////////////////////////////


module MUX(
    input wire signal,  // Ensure signal is wire (default for inputs)
    input wire [7:0] mux_in1,
    input wire [7:0] mux_in2,
    output reg [7:0] mux_out // Must be 'reg' since it’s assigned in always block
);

initial begin
    mux_out = 8'b0;
end
always @(*) begin
   case(signal)
       1'b0: mux_out = mux_in1;
       1'b1: mux_out = mux_in2;
   endcase
end

endmodule

AND.v
`timescale 1ns / 1ps
//////////////////////////////////////////////////////////////////////////////////
// Company: 
// Engineer: 
// 
// Create Date: 03/10/2025 03:48:42 AM
// Design Name: 
// Module Name: AND
// Project Name: 
// Target Devices: 
// Tool Versions: 
// Description: 
// 
// Dependencies: 
// 
// Revision:
// Revision 0.01 - File Created
// Additional Comments:
// 
//////////////////////////////////////////////////////////////////////////////////


module AND(
input a,
input b,
output c
    );

assign c = a & b;    

endmodule

data_memory.v
`timescale 1ns / 1ps


module data_memory(
input clk,
input [7:0] read_addr,
input [7:0] write_addr,
input [7:0] write_data,
input mem_write,
output reg [7:0] read_data
);

reg [7:0] memory [255:0];
integer i;
initial begin
   
    for (i = 0; i < 256; i = i + 1)
        memory[i] = 8'b0000_1001; // Default to 9
end

always @(*) begin

    if (mem_write) 
        memory[write_addr] <= write_data;
    read_data = memory[read_addr];
end



endmodule

ALU.v
`timescale 1ns / 1ps

module ALU(
    input wire [7:0] data_in1,
    input wire [7:0] data_in2,
    input wire [3:0] opcode,
    input wire ALU_src,
    input wire clk,
    output reg [7:0] result,
    output reg compare
);

always @(*) begin
    compare <= 1'b0;
    if (ALU_src) begin
        case (opcode)
            4'b0000: result <= data_in1 + data_in2;   // ADD
            4'b0001: result <= data_in1 - data_in2;   // SUB
            4'b0010: result <= data_in1 & data_in2;   // AND
            4'b0011: result <= data_in1 | data_in2;   // OR
            4'b0100: result <= data_in1 ^ data_in2;   // XOR
            4'b0101: compare <= (data_in1 == data_in2) ? 1'b1 : 1'b0; // COMPARE
            4'b0110: result <= data_in1 + data_in2;   // ADD for load
            4'b0111: result <= data_in1 + data_in2;   // ADD for store
            default: result <= 8'b00000000; // Default case (avoid latches)
        endcase
    end
end

endmodule

Register_file.v
`timescale 1ns / 1ps


module Register_file(
input clk,
input [3:0] read_reg1,
input [3:0] read_reg2,
input [3:0] write_reg,
input [7:0] write_data,
input reg_write,
output reg [7:0] read_data1,
output reg [7:0] read_data2
);

reg [7:0] register_memory [15:0];
integer i;
initial begin
   
    for (i = 0; i < 16; i = i + 1)
        register_memory[i] = 16'b0000_0000_0000_0101; // Default to 0
//    register_memory[0] = 16'b0001_0000_0001_0010; 
end

always @(*) begin
    if (reg_write) 
        register_memory[write_reg] <= write_data;
end

always @(*) begin
    read_data1 = register_memory[read_reg1];
    read_data2 = register_memory[read_reg2];
end


endmodule

control_unit.v
`timescale 1ns / 1ps
//////////////////////////////////////////////////////////////////////////////////
// Company: 
// Engineer: 
// 
// Create Date: 03/03/2025 10:57:49 PM
// Design Name: 
// Module Name: control_unit
// Project Name: 
// Target Devices: 
// Tool Versions: 
// Description: 
// 
// Dependencies: 
// 
// Revision:
// Revision 0.01 - File Created
// Additional Comments:
// 
//////////////////////////////////////////////////////////////////////////////////

module control_unit(
    input wire [3:0] opcode,     // Opcode as input
    output reg reg_write,        // Control signal for Register Write
    output reg branch,
    output reg ALU_src,
    output reg load
);

initial begin
reg_write = 1'b0;
branch = 1'b0;
ALU_src = 1'b0;
end
always @(*) begin
reg_write = 1'b0;
branch = 1'b0;
ALU_src = 1'b0;
load = 1'b0;

if (opcode < 5) begin 
    // R-type instruction execution 
    reg_write = 1'b1;
    ALU_src = 1'b1;
end
else begin
    case (opcode)
        4'b0101: begin // branch if equal BNE
            ALU_src = 1'b1;
            branch = 1'b1;
        end
        4'b0110: begin // load instruction
            ALU_src = 1'b1;
            load = 1'b1;
            reg_write = 1'b1;
        end
    endcase
end
    
    

    
end

endmodule

instruction_decoder.v
module instruction_decoder(
    input wire [15:0] instruction,  // Instruction from Instruction Memory
    output reg [3:0] opcode,        // ALU Operation
    output reg [3:0] read_reg1,     // Source Register 1
    output reg [3:0] read_reg2,     // Source Register 2
    output reg [3:0] write_reg,     // Destination Register
    output reg [7:0] immediate      // Immediate Value
);

reg [7:0] extended_value;

always @(*) begin
    opcode    = instruction[15:12]; // Extract opcode (4 bits)
    read_reg1 = instruction[11:8];  // Extract Rs (source register 1)
    read_reg2 = instruction[7:4];   // Extract Rt (source register 2)
    
    if (opcode < 4'b0101) begin // R-type instruction
        write_reg  = instruction[3:0];   // Extract Rd (destination register)
        immediate  = 4'b0000;            // No immediate value in R-type
    end else begin
        
        extended_value = {4'b0000, instruction[3:0]}; // Zero-extend to 8 bits
        
        
        case (opcode)
                    4'b0101: begin // BEQ
                        write_reg  = 4'b0000;            // No destination register in I-type
                        immediate  = extended_value;   // Extract immediate value
                    end
                    4'b0110: begin // LOAD
                        write_reg  = instruction[11:8];            // No destination register in I-type
                        immediate  = extended_value;   // Extract immediate value
                    end
        endcase
    end
end

endmodule

instruction_memory.v
`timescale 1ns / 1ps


module instruction_memory(
input wire [3:0] addr,
output wire [15:0] instruction
);

reg [15:0] register_memory [15:0];

assign instruction = register_memory[addr];

integer i;
initial begin
   
    for (i = 0; i < 16; i = i + 1)
        register_memory[i] = 16'b0000_0000_0000_0000; // Default to 0
    register_memory[0] = 16'b0110_0000_0001_0110; 
    register_memory[1] = 16'b0000_0000_0010_0100;   
    register_memory[2] = 16'b0110_0000_0100_0101;  
    register_memory[3] = 16'b0110_0000_0101_0111;  
    register_memory[4] = 16'b0001_0000_1100_1011;  
    register_memory[5] = 16'b0101_0000_0001_0000;  
    register_memory[6] = 16'b0101_0000_0001_0010;  
    register_memory[7] = 16'b0011_0100_1100_1011;  
end





endmodule

program_counter.v
`timescale 1ns / 1ps

module program_counter(
    input clk,
    input rst,               
    input [7:0] pc_increment, // Lower 4 bits of 8-bit input
    output reg [3:0] instruction_addr
);

    always @(posedge clk or posedge rst) begin
        if (rst)
            instruction_addr <= 4'b0000;   // Reset counter
        else if (pc_increment[3:0] == 4'b0000)
            instruction_addr <= instruction_addr + 4'b0001;  // Increment by 1 when pc_increment is 0
        else
            instruction_addr <= instruction_addr + pc_increment[3:0]; // Normal increment
    end

endmodule

tb_RISC_16.v
`timescale 1ns / 1ps

module tb_RISC_16;

    // Testbench signals
    reg clk;
    reg rst;
    wire [3:0] instruction_addr;
    wire [15:0] instruction;
    
    wire [3:0] opcode;   // ALU Operation
    wire [3:0] read_reg1; // Source Register 1
    wire [3:0] read_reg2; // Source Register 2
    wire [3:0] write_reg; // Destination Register
    wire [7:0] write_data;
    wire [7:0] read_data1;
    wire [7:0] read_data2;
    wire [7:0] immediate;
    wire compare;
    
    //data memory
    wire [7:0] read_data;
    wire [7:0] write_addr;
    wire [7:0] write_mem_data;
    wire mem_write;
    wire load_signal;
    
    // Control signals
    wire reg_write;        // Control signal for Register Write
    wire ALU_src;
    wire branch;
    
    wire branch_increment_signal;
    wire [7:0] pc_increment;
    
    wire [7:0] alu_result;
    wire [7:0] read_data1_mux;
    
    // Instantiate the 8-bit counter module
    program_counter uut (
        .clk(clk),
        .rst(rst),
        .instruction_addr(instruction_addr),
        .pc_increment(pc_increment)
    );
    
    instruction_memory im(
      .addr(instruction_addr),
      .instruction(instruction)
    );
    
    instruction_decoder id(
    .opcode(opcode),
    .read_reg1(read_reg1),
    .read_reg2(read_reg2),
    .write_reg(write_reg),
    .instruction(instruction),
    .immediate(immediate)
    );
    
    control_unit cu(
    .opcode(opcode),
    .branch(branch),
    .ALU_src(ALU_src),
    .reg_write(reg_write),
    .load(load_signal)
    );
    
    Register_file rf(
    .read_reg1(read_reg1),
    .read_reg2(read_reg2),
    .write_reg(write_reg),
    .write_data(write_data),
    .read_data1(read_data1),
    .read_data2(read_data2),
    .reg_write(reg_write)
    );
    
    ALU alu(
    .data_in1(read_data1_mux),
    .data_in2(read_data2),
    .opcode(opcode),
    .clk(clk),
    .result(alu_result),
    .ALU_src(ALU_src),
    .compare(compare)
    );
    
    data_memory mm(
    .read_addr(alu_result),
    .write_addr(write_addr),
    .write_data(write_mem_data),
    .mem_write(mem_write),
    .read_data(read_data)
    );
    
    MUX memory_ALU_mux(
    .signal(load_signal),
    .mux_in2(read_data),
    .mux_in1(alu_result),
    .mux_out(write_data)
    );
    
    AND branch_ALU(
    .a(branch),
    .b(compare),
    .c(branch_increment_signal)
    );
    
     MUX alu_input_selector(
    .signal(load_signal),
    .mux_in2(immediate),
    .mux_in1(read_data1),
    .mux_out(read_data1_mux)
    );
    
    MUX branch_mux(
    .signal(branch_increment_signal),
    .mux_in2(immediate),
    .mux_in1(8'b1),
    .mux_out(pc_increment)
    );
    


    // Clock generation (10ns period -> 100MHz clock)
    always #10 clk = ~clk;

initial begin
    // Enable VCD dumping
    $dumpfile("waveform.vcd");  // Name of the output waveform file
    $dumpvars(0, tb_RISC_16);    // Dump all variables in the module
    clk = 0;
    rst = 0;  
    #10 rst = 1; // Release reset after 10ns
    #10 rst = 0;
    


    clk = 1'b0;
    // forever begin
    //   #1 clk = ~clk;
    // end

    #10
    clk = ~clk;
    // #10
    // clk = ~clk;
    // #10
    // clk = ~clk;
    // #10
    // clk = ~clk;
    // #10
    // clk = ~clk;
    // #10
    // clk = ~clk;
    // #10
    // clk = ~clk;



    #500;  // Let the simulation run for a longer time
    $finish;  // Stop simulation
end


 // Clock generation
    // always #5 clk = ~clk; // 10ns period (5ns high, 5ns low)

    // initial begin
    //     // Initialize signals
    //      $dumpfile("waveform.vcd");  // Name of the output waveform file
    //     clk = 0;
    //     rst = 1;
    //     // pc_increment = 4'b0010; // Increment by 2
    //     clk = 1;
        
    //     #10 rst = 0;  // Release reset after 10ns
    //     #600 $finish; // Run simulation for 600ns
    // end

    // Monitor changes
    initial begin
        $monitor("Time: %0t | clk: %b | rst: %b | pc_increment: %b | instruction_addr: %b", $time, clk, rst, pc_increment, instruction_addr);
    end


//always #5 clk = ~clk; // Toggle clock every 5ns (10ns period)

endmodule

waveform.vcd
$date
	Tue Mar 18 21:37:37 2025
$end
$version
	Icarus Verilog
$end
$timescale
	1ps
$end
$scope module tb_RISC_16 $end
$var wire 1 ! mem_write $end
$var wire 8 " write_addr [7:0] $end
$var wire 8 # write_mem_data [7:0] $end
$var wire 4 $ write_reg [3:0] $end
$var wire 8 % write_data [7:0] $end
$var wire 1 & reg_write $end
$var wire 4 ' read_reg2 [3:0] $end
$var wire 4 ( read_reg1 [3:0] $end
$var wire 8 ) read_data2 [7:0] $end
$var wire 8 * read_data1_mux [7:0] $end
$var wire 8 + read_data1 [7:0] $end
$var wire 8 , read_data [7:0] $end
$var wire 8 - pc_increment [7:0] $end
$var wire 4 . opcode [3:0] $end
$var wire 1 / load_signal $end
$var wire 4 0 instruction_addr [3:0] $end
$var wire 16 1 instruction [15:0] $end
$var wire 8 2 immediate [7:0] $end
$var wire 1 3 compare $end
$var wire 1 4 branch_increment_signal $end
$var wire 1 5 branch $end
$var wire 8 6 alu_result [7:0] $end
$var wire 1 7 ALU_src $end
$var reg 1 8 clk $end
$var reg 1 9 rst $end
$scope module alu $end
$var wire 1 8 clk $end
$var wire 4 : opcode [3:0] $end
$var wire 8 ; data_in2 [7:0] $end
$var wire 8 < data_in1 [7:0] $end
$var wire 1 7 ALU_src $end
$var reg 1 3 compare $end
$var reg 8 = result [7:0] $end
$upscope $end
$scope module alu_input_selector $end
$var wire 1 / signal $end
$var wire 8 > mux_in2 [7:0] $end
$var wire 8 ? mux_in1 [7:0] $end
$var reg 8 @ mux_out [7:0] $end
$upscope $end
$scope module branch_ALU $end
$var wire 1 3 b $end
$var wire 1 4 c $end
$var wire 1 5 a $end
$upscope $end
$scope module branch_mux $end
$var wire 8 A mux_in1 [7:0] $end
$var wire 1 4 signal $end
$var wire 8 B mux_in2 [7:0] $end
$var reg 8 C mux_out [7:0] $end
$upscope $end
$scope module cu $end
$var wire 4 D opcode [3:0] $end
$var reg 1 7 ALU_src $end
$var reg 1 5 branch $end
$var reg 1 / load $end
$var reg 1 & reg_write $end
$upscope $end
$scope module id $end
$var wire 16 E instruction [15:0] $end
$var reg 8 F extended_value [7:0] $end
$var reg 8 G immediate [7:0] $end
$var reg 4 H opcode [3:0] $end
$var reg 4 I read_reg1 [3:0] $end
$var reg 4 J read_reg2 [3:0] $end
$var reg 4 K write_reg [3:0] $end
$upscope $end
$scope module im $end
$var wire 16 L instruction [15:0] $end
$var wire 4 M addr [3:0] $end
$var integer 32 N i [31:0] $end
$upscope $end
$scope module memory_ALU_mux $end
$var wire 8 O mux_in1 [7:0] $end
$var wire 1 / signal $end
$var wire 8 P mux_in2 [7:0] $end
$var reg 8 Q mux_out [7:0] $end
$upscope $end
$scope module mm $end
$var wire 1 R clk $end
$var wire 1 ! mem_write $end
$var wire 8 S read_addr [7:0] $end
$var wire 8 T write_addr [7:0] $end
$var wire 8 U write_data [7:0] $end
$var reg 8 V read_data [7:0] $end
$var integer 32 W i [31:0] $end
$upscope $end
$scope module rf $end
$var wire 1 X clk $end
$var wire 4 Y read_reg1 [3:0] $end
$var wire 4 Z read_reg2 [3:0] $end
$var wire 1 & reg_write $end
$var wire 8 [ write_data [7:0] $end
$var wire 4 \ write_reg [3:0] $end
$var reg 8 ] read_data1 [7:0] $end
$var reg 8 ^ read_data2 [7:0] $end
$var integer 32 _ i [31:0] $end
$upscope $end
$scope module uut $end
$var wire 1 8 clk $end
$var wire 8 ` pc_increment [7:0] $end
$var wire 1 9 rst $end
$var reg 4 a instruction_addr [3:0] $end
$upscope $end
$upscope $end
$enddefinitions $end
#0
$dumpvars
bx a
b1 `
b10000 _
bx ^
bx ]
bx \
b0 [
bx Z
bx Y
zX
b100000000 W
bx V
bz U
bz T
bx S
zR
b0 Q
bx P
bx O
b10000 N
bx M
bx L
bx K
bx J
bx I
bx H
bx G
bx F
bx E
bx D
b1 C
bx B
b1 A
b0 @
bx ?
bx >
bx =
b0 <
bx ;
bx :
09
08
07
bx 6
05
04
03
bx 2
bx 1
bx 0
x/
bx .
b1 -
bx ,
bx +
b0 *
bx )
bx (
bx '
0&
b0 %
bx $
bz #
bz "
z!
$end
#10000
b1001 ,
b1001 P
b1001 V
b1011 6
b1011 =
b1011 O
b1011 S
b1001 %
b1001 Q
b1001 [
b110 *
b110 <
b110 @
b101 )
b101 ;
b101 ^
b1001 +
b1001 ?
b1001 ]
1&
17
1/
b110 2
b110 >
b110 B
b110 G
b0 $
b0 K
b0 \
b110 F
b1 '
b1 J
b1 Z
b0 (
b0 I
b0 Y
b110 .
b110 :
b110 D
b110 H
b110000000010110 1
b110000000010110 E
b110000000010110 L
b0 0
b0 M
b0 a
19
18
#20000
09
08
#30000
b1110 6
b1110 =
b1110 O
b1110 S
b1110 %
b1110 Q
b1110 [
b1001 *
b1001 <
b1001 @
0/
17
1&
b0 2
b0 >
b0 B
b0 G
b100 $
b100 K
b100 \
b10 '
b10 J
b10 Z
b0 .
b0 :
b0 D
b0 H
b100100 1
b100100 E
b100100 L
b1 0
b1 M
b1 a
08
#40000
b10011 6
b10011 =
b10011 O
b10011 S
b1001 %
b1001 Q
b1001 [
b101 *
b101 <
b101 @
b1110 )
b1110 ;
b1110 ^
1/
17
1&
b101 2
b101 >
b101 B
b101 G
b0 $
b0 K
b0 \
b101 F
b100 '
b100 J
b100 Z
b110 .
b110 :
b110 D
b110 H
b110000001000101 1
b110000001000101 E
b110000001000101 L
b10 0
b10 M
b10 a
18
#50000
08
#60000
b1100 6
b1100 =
b1100 O
b1100 S
b111 *
b111 <
b111 @
b101 )
b101 ;
b101 ^
b111 2
b111 >
b111 B
b111 G
b111 F
b101 '
b101 J
b101 Z
b110000001010111 1
b110000001010111 E
b110000001010111 L
b11 0
b11 M
b11 a
18
#70000
08
#80000
b100 6
b100 =
b100 O
b100 S
b100 %
b100 Q
b100 [
b1001 *
b1001 <
b1001 @
0/
17
1&
b0 2
b0 >
b0 B
b0 G
b1011 $
b1011 K
b1011 \
b1100 '
b1100 J
b1100 Z
b1 .
b1 :
b1 D
b1 H
b1000011001011 1
b1000011001011 E
b1000011001011 L
b100 0
b100 M
b100 a
18
#90000
08
#100000
15
17
0&
b0 $
b0 K
b0 \
b0 F
b1 '
b1 J
b1 Z
b101 .
b101 :
b101 D
b101 H
b101000000010000 1
b101000000010000 E
b101000000010000 L
b101 0
b101 M
b101 a
18
#110000
08
#120000
b10 2
b10 >
b10 B
b10 G
b10 F
b101000000010010 1
b101000000010010 E
b101000000010010 L
b110 0
b110 M
b110 a
18
#130000
08
#140000
b1111 %
b1111 Q
b1111 [
b1111 6
b1111 =
b1111 O
b1111 S
b1110 *
b1110 <
b1110 @
b1110 +
b1110 ?
b1110 ]
1&
17
05
b0 2
b0 >
b0 B
b0 G
b1011 $
b1011 K
b1011 \
b1100 '
b1100 J
b1100 Z
b100 (
b100 I
b100 Y
b11 .
b11 :
b11 D
b11 H
b11010011001011 1
b11010011001011 E
b11010011001011 L
b111 0
b111 M
b111 a
18
#150000
08
#160000
b0 %
b0 Q
b0 [
b0 6
b0 =
b0 O
b0 S
b0 *
b0 <
b0 @
b0 )
b0 ;
b0 ^
b0 +
b0 ?
b0 ]
17
1&
b0 $
b0 K
b0 \
b0 '
b0 J
b0 Z
b0 (
b0 I
b0 Y
b0 .
b0 :
b0 D
b0 H
b0 1
b0 E
b0 L
b1000 0
b1000 M
b1000 a
18
#170000
08
#180000
b1001 0
b1001 M
b1001 a
18
#190000
08
#200000
b1010 0
b1010 M
b1010 a
18
#210000
08
#220000
b1011 0
b1011 M
b1011 a
18
#230000
08
#240000
b1100 0
b1100 M
b1100 a
18
#250000
08
#260000
b1101 0
b1101 M
b1101 a
18
#270000
08
#280000
b1110 0
b1110 M
b1110 a
18
#290000
08
#300000
b1111 0
b1111 M
b1111 a
18
#310000
08
#320000
b1001 +
b1001 ?
b1001 ]
b1011 6
b1011 =
b1011 O
b1011 S
b1001 %
b1001 Q
b1001 [
b110 *
b110 <
b110 @
b101 )
b101 ;
b101 ^
1/
17
1&
b110 2
b110 >
b110 B
b110 G
b110 F
b1 '
b1 J
b1 Z
b110 .
b110 :
b110 D
b110 H
b110000000010110 1
b110000000010110 E
b110000000010110 L
b0 0
b0 M
b0 a
18
#330000
08
#340000
b1110 6
b1110 =
b1110 O
b1110 S
b1110 %
b1110 Q
b1110 [
b1001 *
b1001 <
b1001 @
0/
17
1&
b0 2
b0 >
b0 B
b0 G
b100 $
b100 K
b100 \
b10 '
b10 J
b10 Z
b0 .
b0 :
b0 D
b0 H
b100100 1
b100100 E
b100100 L
b1 0
b1 M
b1 a
18
#350000
08
#360000
b10011 6
b10011 =
b10011 O
b10011 S
b1001 %
b1001 Q
b1001 [
b101 *
b101 <
b101 @
b1110 )
b1110 ;
b1110 ^
1/
17
1&
b101 2
b101 >
b101 B
b101 G
b0 $
b0 K
b0 \
b101 F
b100 '
b100 J
b100 Z
b110 .
b110 :
b110 D
b110 H
b110000001000101 1
b110000001000101 E
b110000001000101 L
b10 0
b10 M
b10 a
18
#370000
08
#380000
b1100 6
b1100 =
b1100 O
b1100 S
b111 *
b111 <
b111 @
b101 )
b101 ;
b101 ^
b111 2
b111 >
b111 B
b111 G
b111 F
b101 '
b101 J
b101 Z
b110000001010111 1
b110000001010111 E
b110000001010111 L
b11 0
b11 M
b11 a
18
#390000
08
#400000
b100 6
b100 =
b100 O
b100 S
b100 %
b100 Q
b100 [
b1001 *
b1001 <
b1001 @
0/
17
1&
b0 2
b0 >
b0 B
b0 G
b1011 $
b1011 K
b1011 \
b1100 '
b1100 J
b1100 Z
b1 .
b1 :
b1 D
b1 H
b1000011001011 1
b1000011001011 E
b1000011001011 L
b100 0
b100 M
b100 a
18
#410000
08
#420000
15
17
0&
b0 $
b0 K
b0 \
b0 F
b1 '
b1 J
b1 Z
b101 .
b101 :
b101 D
b101 H
b101000000010000 1
b101000000010000 E
b101000000010000 L
b101 0
b101 M
b101 a
18
#430000
08
#440000
b10 2
b10 >
b10 B
b10 G
b10 F
b101000000010010 1
b101000000010010 E
b101000000010010 L
b110 0
b110 M
b110 a
18
#450000
08
#460000
b1111 %
b1111 Q
b1111 [
b1111 6
b1111 =
b1111 O
b1111 S
b1110 *
b1110 <
b1110 @
b1110 +
b1110 ?
b1110 ]
1&
17
05
b0 2
b0 >
b0 B
b0 G
b1011 $
b1011 K
b1011 \
b1100 '
b1100 J
b1100 Z
b100 (
b100 I
b100 Y
b11 .
b11 :
b11 D
b11 H
b11010011001011 1
b11010011001011 E
b11010011001011 L
b111 0
b111 M
b111 a
18
#470000
08
#480000
b0 %
b0 Q
b0 [
b0 6
b0 =
b0 O
b0 S
b0 *
b0 <
b0 @
b0 )
b0 ;
b0 ^
b0 +
b0 ?
b0 ]
17
1&
b0 $
b0 K
b0 \
b0 '
b0 J
b0 Z
b0 (
b0 I
b0 Y
b0 .
b0 :
b0 D
b0 H
b0 1
b0 E
b0 L
b1000 0
b1000 M
b1000 a
18
#490000
08
#500000
b1001 0
b1001 M
b1001 a
18
#510000
08
#520000
b1010 0
b1010 M
b1010 a
18
