MUX.v
`timescale 1ns / 1ps
//////////////////////////////////////////////////////////////////////////////////
// Company: 
// Engineer: 
// 
// Create Date: 03/10/2025 02:27:47 AM
// Design Name: 
// Module Name: MUX
// Project Name: 
// Target Devices: 
// Tool Versions: 
// Description: 
// 
// Dependencies: 
// 
// Revision:
// Revision 0.01 - File Created
// Additional Comments:
// 
//////////////////////////////////////////////////////////////////////////////////


module MUX(
    input wire signal,  // Ensure signal is wire (default for inputs)
    input wire [7:0] mux_in1,
    input wire [7:0] mux_in2,
    output reg [7:0] mux_out // Must be 'reg' since it’s assigned in always block
);

initial begin
    mux_out = 8'b0;
end
always @(*) begin
   case(signal)
       1'b0: mux_out = mux_in1;
       1'b1: mux_out = mux_in2;
   endcase
end

endmodule

AND.v
`timescale 1ns / 1ps
//////////////////////////////////////////////////////////////////////////////////
// Company: 
// Engineer: 
// 
// Create Date: 03/10/2025 03:48:42 AM
// Design Name: 
// Module Name: AND
// Project Name: 
// Target Devices: 
// Tool Versions: 
// Description: 
// 
// Dependencies: 
// 
// Revision:
// Revision 0.01 - File Created
// Additional Comments:
// 
//////////////////////////////////////////////////////////////////////////////////


module AND(
input a,
input b,
output c
    );

assign c = a & b;    

endmodule

data_memory.v
`timescale 1ns / 1ps


module data_memory(
input clk,
input [7:0] read_addr,
input [7:0] write_addr,
input [7:0] write_data,
input mem_write,
output reg [7:0] read_data
);

reg [7:0] memory [255:0];
integer i;
initial begin
   
    for (i = 0; i < 256; i = i + 1)
        memory[i] = 8'b0000_1001; // Default to 9
end

always @(*) begin

    if (mem_write) 
        memory[write_addr] <= write_data;
    read_data = memory[read_addr];
end



endmodule

ALU.v
`timescale 1ns / 1ps

module ALU(
    input wire [7:0] data_in1,
    input wire [7:0] data_in2,
    input wire [3:0] opcode,
    input wire ALU_src,
    input wire clk,
    output reg [7:0] result,
    output reg compare
);

always @(*) begin
    compare <= 1'b0;
    if (ALU_src) begin
        case (opcode)
            4'b0000: result <= data_in1 + data_in2;   // ADD
            4'b0001: result <= data_in1 - data_in2;   // SUB
            4'b0010: result <= data_in1 & data_in2;   // AND
            4'b0011: result <= data_in1 | data_in2;   // OR
            4'b0100: result <= data_in1 ^ data_in2;   // XOR
            4'b0101: compare <= (data_in1 == data_in2) ? 1'b1 : 1'b0; // COMPARE
            4'b0110: result <= data_in1 + data_in2;   // ADD for load
            4'b0111: result <= data_in1 + data_in2;   // ADD for store
            default: result <= 8'b00000000; // Default case (avoid latches)
        endcase
    end
end

endmodule

Register_file.v
`timescale 1ns / 1ps


module Register_file(
input clk,
input [3:0] read_reg1,
input [3:0] read_reg2,
input [3:0] write_reg,
input [7:0] write_data,
input reg_write,
output reg [7:0] read_data1,
output reg [7:0] read_data2
);

reg [7:0] register_memory [15:0];
integer i;
initial begin
   
    for (i = 0; i < 16; i = i + 1)
        register_memory[i] = 16'b0000_0000_0000_0101; // Default to 0
//    register_memory[0] = 16'b0001_0000_0001_0010; 
end

always @(*) begin
    if (reg_write) 
        register_memory[write_reg] <= write_data;
end

always @(*) begin
    read_data1 = register_memory[read_reg1];
    read_data2 = register_memory[read_reg2];
end


endmodule

control_unit.v
`timescale 1ns / 1ps
//////////////////////////////////////////////////////////////////////////////////
// Company: 
// Engineer: 
// 
// Create Date: 03/03/2025 10:57:49 PM
// Design Name: 
// Module Name: control_unit
// Project Name: 
// Target Devices: 
// Tool Versions: 
// Description: 
// 
// Dependencies: 
// 
// Revision:
// Revision 0.01 - File Created
// Additional Comments:
// 
//////////////////////////////////////////////////////////////////////////////////

module control_unit(
    input wire [3:0] opcode,     // Opcode as input
    output reg reg_write,        // Control signal for Register Write
    output reg branch,
    output reg ALU_src,
    output reg load,
    output reg mem_write,
    output reg jump 
);

initial begin
reg_write = 1'b0;
branch = 1'b0;
ALU_src = 1'b0;
load = 1'b0;
mem_write = 1'b0;
jump = 1'b0;
end

always @(*) begin
reg_write = 1'b0;
branch = 1'b0;
ALU_src = 1'b0;
load = 1'b0;
mem_write = 1'b0;
jump = 1'b0;


if (opcode < 7) begin 
    // R-type instruction execution 
    reg_write = 1'b1;
    ALU_src = 1'b1;
end
else begin
    case (opcode)
        4'b0111: begin // branch if equal BQE
            ALU_src = 1'b1;
            branch = 1'b1;
        end
        4'b1001: begin // load instruction
            ALU_src = 1'b1;
            load = 1'b1;
            reg_write = 1'b1;
        end
        4'b1010: begin // store instruction 
            ALU_src = 1'b1;
            load = 1'b1;
            mem_write = 1'b1;
        end
        4'b1011: begin // jump
            jump = 1'b1;
        end
    endcase
end
    
    

    
end

endmodule

instruction_decoder.v
module instruction_decoder(
    input wire [15:0] instruction,  // Instruction from Instruction Memory
    output reg [3:0] opcode,        // ALU Operation
    output reg [3:0] read_reg1,     // Source Register 1
    output reg [3:0] read_reg2,     // Source Register 2
    output reg [3:0] write_reg,     // Destination Register
    output reg [7:0] immediate      // Immediate Value
);

reg [7:0] extended_value;

always @(*) begin
    opcode    = instruction[15:12]; // Extract opcode (4 bits)
    read_reg1 = instruction[11:8];  // Extract Rs (source register 1)
    read_reg2 = instruction[7:4];   // Extract Rt (source register 2)
    
    if (opcode < 4'b0101) begin // R-type instruction
        write_reg  = instruction[3:0];   // Extract Rd (destination register)
        immediate  = 4'b0000;            // No immediate value in R-type
    end else begin
        
        extended_value = {4'b0000, instruction[3:0]}; // Zero-extend to 8 bits
        
        
        case (opcode)
                    4'b0101: begin // BEQ
                        write_reg  = 4'b0000;            // No destination register in I-type
                        immediate  = extended_value;   // Extract immediate value
                    end
                    4'b0110: begin // LOAD
                        write_reg  = instruction[11:8];            // No destination register in I-type
                        immediate  = extended_value;   // Extract immediate value
                    end
        endcase
    end
end

endmodule

instruction_memory.v
`timescale 1ns / 1ps


module instruction_memory(
input wire [3:0] addr,
output wire [15:0] instruction
);

reg [15:0] register_memory [15:0];

assign instruction = register_memory[addr];

integer i;
initial begin
   
    for (i = 0; i < 16; i = i + 1)
        register_memory[i] = 16'b0000_0000_0000_0000; // Default to 0
        //opcode_first_second_destination
        //opcode_first_second_immediate 
        //opcode_first_second_immediate 
    register_memory[0] = 16'b1010_0000_0001_0110; // STORE $r0 6($r1) : r1+6 = r0
    register_memory[1] = 16'b1001_0101_0001_0110; // LOAD $r0 6($r1) : r0 = r1+6
    register_memory[2] = 16'b0101_0000_1000_0101;  // shift right
    register_memory[3] = 16'b0110_0101_1000_0111;  // shift left
    register_memory[4] = 16'b1000_0000_0111_0010;  // branch if not equal   
    register_memory[5] = 16'b0101_0000_0001_0000;  
    register_memory[6] = 16'b0101_0000_0001_0010;  
    register_memory[7] = 16'b1011_0000_0000_0000; // jump to 0 instruction addr  
end





endmodule

program_counter.v
`timescale 1ns / 1ps

module program_counter(
    input clk,
    input rst,               
    input [7:0] pc_increment, // Lower 4 bits of 8-bit input
    input jump, 
    input [7:0] jump_label,
    output reg [3:0] instruction_addr
    
);

    always @(posedge clk or posedge rst) begin
        if (rst)
            instruction_addr <= 4'b0000;   // Reset counter
        else if (pc_increment[3:0] == 4'b0000)
            instruction_addr <= instruction_addr + 4'b0001;  // Increment by 1 when pc_increment is 0
        else if (jump)
            instruction_addr <= jump_label[3:0];  // jump to address
            // instruction_addr <= 4'b0010;  // jump to address
        else
            instruction_addr <= instruction_addr + pc_increment[3:0]; // Normal increment
    end

endmodule

tb_RISC_16.v
`timescale 1ns / 1ps

module tb_RISC_16;

    // Testbench signals
    reg clk;
    reg rst;
    wire [3:0] instruction_addr;
    wire [15:0] instruction;
    
    wire [3:0] opcode;   // ALU Operation
    wire [3:0] read_reg1; // Source Register 1
    wire [3:0] read_reg2; // Source Register 2
    wire [3:0] write_reg; // Destination Register
    wire [7:0] write_data;
    wire [7:0] read_data1;
    wire [7:0] read_data2;
    wire [7:0] immediate;
    wire compare;
    
    //data memory
    wire [7:0] read_data;
    // wire [7:0] write_addr;
    // wire [7:0] read_data1;
    wire mem_write;
    wire load_signal;
    
    // Control signals
    wire reg_write;        // Control signal for Register Write
    wire ALU_src;
    wire branch;
    wire jump;
    
    wire branch_increment_signal;
    wire [7:0] pc_increment;
    
    wire [7:0] alu_result;
    wire [7:0] read_data1_mux;
    
    // Instantiate the 8-bit counter module
    program_counter uut (
        .clk(clk),
        .rst(rst),
        .instruction_addr(instruction_addr),
        .pc_increment(pc_increment),
        .jump(jump),
        .jump_label(immediate)
    );
    
    instruction_memory im(
      .addr(instruction_addr),
      .instruction(instruction)
    );
    
    instruction_decoder id(
    .opcode(opcode),
    .read_reg1(read_reg1),
    .read_reg2(read_reg2),
    .write_reg(write_reg),
    .instruction(instruction),
    .immediate(immediate)
    );
    
    control_unit cu(
    .opcode(opcode),
    .branch(branch),
    .ALU_src(ALU_src),
    .reg_write(reg_write),
    .load(load_signal),
    .mem_write(mem_write),
    .jump(jump)
    );
    
    Register_file rf(
    .read_reg1(read_reg1),
    .read_reg2(read_reg2),
    .write_reg(write_reg),
    .write_data(write_data),
    .read_data1(read_data1),
    .read_data2(read_data2),
    .reg_write(reg_write)
    );
    
    ALU alu(
    .data_in1(read_data1_mux),
    .data_in2(read_data2),
    .opcode(opcode),
    .clk(clk),
    .result(alu_result),
    .ALU_src(ALU_src),
    .compare(compare)
    );
    
    data_memory mm(
    .read_addr(alu_result),
    .write_addr(alu_result),
    .write_data(read_data1),
    .mem_write(mem_write),
    .read_data(read_data)
    );
    
    MUX memory_ALU_mux(
    .signal(load_signal),
    .mux_in2(read_data),
    .mux_in1(alu_result),
    .mux_out(write_data)
    );
    
    AND branch_ALU(
    .a(branch),
    .b(compare),
    .c(branch_increment_signal)
    );
    
     MUX alu_input_selector(
    .signal(load_signal),
    .mux_in2(immediate),
    .mux_in1(read_data1),
    .mux_out(read_data1_mux)
    );
    
    MUX branch_mux(
    .signal(branch_increment_signal),
    .mux_in2(immediate),
    .mux_in1(8'b1),
    .mux_out(pc_increment)
    );
    


    // Clock generation (10ns period -> 100MHz clock)
    always #10 clk = ~clk;

initial begin
    // Enable VCD dumping
    $dumpfile("waveform.vcd");  // Name of the output waveform file
    $dumpvars(0, tb_RISC_16);    // Dump all variables in the module
    clk = 0;
    rst = 0;  
    #10 rst = 1; // Release reset after 10ns
    #10 rst = 0;
    


    clk = 1'b0;
    // forever begin
    //   #1 clk = ~clk;
    // end

    #10
    clk = ~clk;



    #500;  // Let the simulation run for a longer time
    $finish;  // Stop simulation
end




    // Monitor changes
    initial begin
        $monitor("Time: %0t | clk: %b | rst: %b | pc_increment: %b | instruction_addr: %b", $time, clk, rst, pc_increment, instruction_addr);
    end


//always #5 clk = ~clk; // Toggle clock every 5ns (10ns period)

endmodule

waveform.vcd
$date
	Tue Apr 08 23:52:49 2025
$end
$version
	Icarus Verilog
$end
$timescale
	1ps
$end
$scope module tb_RISC_16 $end
$var wire 4 ! write_reg [3:0] $end
$var wire 8 " write_data [7:0] $end
$var wire 1 # reg_write $end
$var wire 4 $ read_reg2 [3:0] $end
$var wire 4 % read_reg1 [3:0] $end
$var wire 8 & read_data2 [7:0] $end
$var wire 8 ' read_data1_mux [7:0] $end
$var wire 8 ( read_data1 [7:0] $end
$var wire 8 ) read_data [7:0] $end
$var wire 8 * pc_increment [7:0] $end
$var wire 4 + opcode [3:0] $end
$var wire 1 , mem_write $end
$var wire 1 - load_signal $end
$var wire 1 . jump $end
$var wire 4 / instruction_addr [3:0] $end
$var wire 16 0 instruction [15:0] $end
$var wire 8 1 immediate [7:0] $end
$var wire 1 2 compare $end
$var wire 1 3 branch_increment_signal $end
$var wire 1 4 branch $end
$var wire 8 5 alu_result [7:0] $end
$var wire 1 6 ALU_src $end
$var reg 1 7 clk $end
$var reg 1 8 rst $end
$scope module alu $end
$var wire 1 7 clk $end
$var wire 4 9 opcode [3:0] $end
$var wire 8 : data_in2 [7:0] $end
$var wire 8 ; data_in1 [7:0] $end
$var wire 1 6 ALU_src $end
$var reg 1 2 compare $end
$var reg 8 < result [7:0] $end
$upscope $end
$scope module alu_input_selector $end
$var wire 1 - signal $end
$var wire 8 = mux_in2 [7:0] $end
$var wire 8 > mux_in1 [7:0] $end
$var reg 8 ? mux_out [7:0] $end
$upscope $end
$scope module branch_ALU $end
$var wire 1 2 b $end
$var wire 1 3 c $end
$var wire 1 4 a $end
$upscope $end
$scope module branch_mux $end
$var wire 8 @ mux_in1 [7:0] $end
$var wire 1 3 signal $end
$var wire 8 A mux_in2 [7:0] $end
$var reg 8 B mux_out [7:0] $end
$upscope $end
$scope module cu $end
$var wire 4 C opcode [3:0] $end
$var reg 1 6 ALU_src $end
$var reg 1 4 branch $end
$var reg 1 . jump $end
$var reg 1 - load $end
$var reg 1 , mem_write $end
$var reg 1 # reg_write $end
$upscope $end
$scope module id $end
$var wire 16 D instruction [15:0] $end
$var reg 8 E extended_value [7:0] $end
$var reg 8 F immediate [7:0] $end
$var reg 4 G opcode [3:0] $end
$var reg 4 H read_reg1 [3:0] $end
$var reg 4 I read_reg2 [3:0] $end
$var reg 4 J write_reg [3:0] $end
$upscope $end
$scope module im $end
$var wire 16 K instruction [15:0] $end
$var wire 4 L addr [3:0] $end
$var integer 32 M i [31:0] $end
$upscope $end
$scope module memory_ALU_mux $end
$var wire 8 N mux_in1 [7:0] $end
$var wire 1 - signal $end
$var wire 8 O mux_in2 [7:0] $end
$var reg 8 P mux_out [7:0] $end
$upscope $end
$scope module mm $end
$var wire 1 Q clk $end
$var wire 1 , mem_write $end
$var wire 8 R read_addr [7:0] $end
$var wire 8 S write_addr [7:0] $end
$var wire 8 T write_data [7:0] $end
$var reg 8 U read_data [7:0] $end
$var integer 32 V i [31:0] $end
$upscope $end
$scope module rf $end
$var wire 1 W clk $end
$var wire 4 X read_reg1 [3:0] $end
$var wire 4 Y read_reg2 [3:0] $end
$var wire 1 # reg_write $end
$var wire 8 Z write_data [7:0] $end
$var wire 4 [ write_reg [3:0] $end
$var reg 8 \ read_data1 [7:0] $end
$var reg 8 ] read_data2 [7:0] $end
$var integer 32 ^ i [31:0] $end
$upscope $end
$scope module uut $end
$var wire 1 7 clk $end
$var wire 1 . jump $end
$var wire 8 _ jump_label [7:0] $end
$var wire 8 ` pc_increment [7:0] $end
$var wire 1 8 rst $end
$var reg 4 a instruction_addr [3:0] $end
$upscope $end
$upscope $end
$enddefinitions $end
#0
$dumpvars
bx a
b1 `
bx _
b10000 ^
bx ]
bx \
bx [
bx Z
bx Y
bx X
zW
b100000000 V
bx U
bx T
bx S
bx R
zQ
bx P
bx O
bx N
b10000 M
bx L
bx K
bx J
bx I
bx H
bx G
bx F
bx E
bx D
bx C
b1 B
bx A
b1 @
bx ?
bx >
bx =
bx <
bx ;
bx :
bx 9
08
07
06
bx 5
04
03
02
bx 1
bx 0
bx /
0.
0-
0,
bx +
b1 *
bx )
bx (
bx '
bx &
bx %
bx $
0#
bx "
bx !
$end
#10000
b101 "
b101 P
b101 Z
b101 )
b101 O
b101 U
b1011 5
b1011 <
b1011 N
b1011 R
b1011 S
b110 '
b110 ;
b110 ?
b101 &
b101 :
b101 ]
b101 (
b101 >
b101 T
b101 \
1,
1-
16
b110 1
b110 =
b110 A
b110 F
b110 _
b0 !
b0 J
b0 [
b110 E
b1 $
b1 I
b1 Y
b0 %
b0 H
b0 X
b1010 +
b1010 9
b1010 C
b1010 G
b1010000000010110 0
b1010000000010110 D
b1010000000010110 K
b0 /
b0 L
b0 a
18
17
#20000
08
07
#30000
1#
0,
1-
16
b101 !
b101 J
b101 [
b101 %
b101 H
b101 X
b1001 +
b1001 9
b1001 C
b1001 G
b1001010100010110 0
b1001010100010110 D
b1001010100010110 K
b1 /
b1 L
b1 a
07
#40000
b1001 )
b1001 O
b1001 U
b0 5
b0 <
b0 N
b0 R
b0 S
b0 "
b0 P
b0 Z
b101 '
b101 ;
b101 ?
0-
16
1#
b0 1
b0 =
b0 A
b0 F
b0 _
b1000 $
b1000 I
b1000 Y
b0 %
b0 H
b0 X
b101 +
b101 9
b101 C
b101 G
b101000010000101 0
b101000010000101 D
b101000010000101 K
b10 /
b10 L
b10 a
17
#50000
07
#60000
b0 5
b0 <
b0 N
b0 R
b0 S
b0 '
b0 ;
b0 ?
b0 (
b0 >
b0 T
b0 \
16
1#
b111 !
b111 J
b111 [
b101 %
b101 H
b101 X
b110 +
b110 9
b110 C
b110 G
b110010110000111 0
b110010110000111 D
b110010110000111 K
b11 /
b11 L
b11 a
17
#70000
07
#80000
b10 *
b10 B
b10 `
13
12
b101 '
b101 ;
b101 ?
b0 &
b0 :
b0 ]
b101 (
b101 >
b101 T
b101 \
14
16
0#
b10 1
b10 =
b10 A
b10 F
b10 _
b0 !
b0 J
b0 [
b10 E
b111 $
b111 I
b111 Y
b0 %
b0 H
b0 X
b1000 +
b1000 9
b1000 C
b1000 G
b1000000001110010 0
b1000000001110010 D
b1000000001110010 K
b100 /
b100 L
b100 a
17
#90000
07
#100000
b0 5
b0 <
b0 N
b0 R
b0 S
02
03
b1 *
b1 B
b1 `
b101 &
b101 :
b101 ]
1#
16
04
b0 1
b0 =
b0 A
b0 F
b0 _
b10 !
b10 J
b10 [
b1 $
b1 I
b1 Y
b101 +
b101 9
b101 C
b101 G
b101000000010010 0
b101000000010010 D
b101000000010010 K
b110 /
b110 L
b110 a
17
#110000
07
#120000
1.
06
0#
b0 !
b0 J
b0 [
b0 E
b0 $
b0 I
b0 Y
b1011 +
b1011 9
b1011 C
b1011 G
b1011000000000000 0
b1011000000000000 D
b1011000000000000 K
b111 /
b111 L
b111 a
17
#130000
07
#140000
b101 )
b101 O
b101 U
b1011 5
b1011 <
b1011 N
b1011 R
b1011 S
b101 "
b101 P
b101 Z
b110 '
b110 ;
b110 ?
1,
1-
16
0.
b110 1
b110 =
b110 A
b110 F
b110 _
b110 E
b1 $
b1 I
b1 Y
b1010 +
b1010 9
b1010 C
b1010 G
b1010000000010110 0
b1010000000010110 D
b1010000000010110 K
b0 /
b0 L
b0 a
17
#150000
07
#160000
b101 (
b101 >
b101 T
b101 \
1#
0,
1-
16
b101 !
b101 J
b101 [
b101 %
b101 H
b101 X
b1001 +
b1001 9
b1001 C
b1001 G
b1001010100010110 0
b1001010100010110 D
b1001010100010110 K
b1 /
b1 L
b1 a
17
#170000
07
#180000
b0 5
b0 <
b0 N
b0 R
b0 S
b0 "
b0 P
b0 Z
b101 '
b101 ;
b101 ?
0-
16
1#
b0 1
b0 =
b0 A
b0 F
b0 _
b1000 $
b1000 I
b1000 Y
b0 %
b0 H
b0 X
b101 +
b101 9
b101 C
b101 G
b101000010000101 0
b101000010000101 D
b101000010000101 K
b10 /
b10 L
b10 a
17
#190000
07
#200000
b0 5
b0 <
b0 N
b0 R
b0 S
b0 '
b0 ;
b0 ?
b0 (
b0 >
b0 T
b0 \
16
1#
b111 !
b111 J
b111 [
b101 %
b101 H
b101 X
b110 +
b110 9
b110 C
b110 G
b110010110000111 0
b110010110000111 D
b110010110000111 K
b11 /
b11 L
b11 a
17
#210000
07
#220000
b10 *
b10 B
b10 `
13
12
b101 '
b101 ;
b101 ?
b0 &
b0 :
b0 ]
b101 (
b101 >
b101 T
b101 \
14
16
0#
b10 1
b10 =
b10 A
b10 F
b10 _
b0 !
b0 J
b0 [
b10 E
b111 $
b111 I
b111 Y
b0 %
b0 H
b0 X
b1000 +
b1000 9
b1000 C
b1000 G
b1000000001110010 0
b1000000001110010 D
b1000000001110010 K
b100 /
b100 L
b100 a
17
#230000
07
#240000
b0 5
b0 <
b0 N
b0 R
b0 S
02
03
b1 *
b1 B
b1 `
b101 &
b101 :
b101 ]
1#
16
04
b0 1
b0 =
b0 A
b0 F
b0 _
b10 !
b10 J
b10 [
b1 $
b1 I
b1 Y
b101 +
b101 9
b101 C
b101 G
b101000000010010 0
b101000000010010 D
b101000000010010 K
b110 /
b110 L
b110 a
17
#250000
07
#260000
1.
06
0#
b0 !
b0 J
b0 [
b0 E
b0 $
b0 I
b0 Y
b1011 +
b1011 9
b1011 C
b1011 G
b1011000000000000 0
b1011000000000000 D
b1011000000000000 K
b111 /
b111 L
b111 a
17
#270000
07
#280000
b1011 5
b1011 <
b1011 N
b1011 R
b1011 S
b101 "
b101 P
b101 Z
b110 '
b110 ;
b110 ?
1,
1-
16
0.
b110 1
b110 =
b110 A
b110 F
b110 _
b110 E
b1 $
b1 I
b1 Y
b1010 +
b1010 9
b1010 C
b1010 G
b1010000000010110 0
b1010000000010110 D
b1010000000010110 K
b0 /
b0 L
b0 a
17
#290000
07
#300000
b101 (
b101 >
b101 T
b101 \
1#
0,
1-
16
b101 !
b101 J
b101 [
b101 %
b101 H
b101 X
b1001 +
b1001 9
b1001 C
b1001 G
b1001010100010110 0
b1001010100010110 D
b1001010100010110 K
b1 /
b1 L
b1 a
17
#310000
07
#320000
b0 5
b0 <
b0 N
b0 R
b0 S
b0 "
b0 P
b0 Z
b101 '
b101 ;
b101 ?
0-
16
1#
b0 1
b0 =
b0 A
b0 F
b0 _
b1000 $
b1000 I
b1000 Y
b0 %
b0 H
b0 X
b101 +
b101 9
b101 C
b101 G
b101000010000101 0
b101000010000101 D
b101000010000101 K
b10 /
b10 L
b10 a
17
#330000
07
#340000
b0 5
b0 <
b0 N
b0 R
b0 S
b0 '
b0 ;
b0 ?
b0 (
b0 >
b0 T
b0 \
16
1#
b111 !
b111 J
b111 [
b101 %
b101 H
b101 X
b110 +
b110 9
b110 C
b110 G
b110010110000111 0
b110010110000111 D
b110010110000111 K
b11 /
b11 L
b11 a
17
#350000
07
#360000
b10 *
b10 B
b10 `
13
12
b101 '
b101 ;
b101 ?
b0 &
b0 :
b0 ]
b101 (
b101 >
b101 T
b101 \
14
16
0#
b10 1
b10 =
b10 A
b10 F
b10 _
b0 !
b0 J
b0 [
b10 E
b111 $
b111 I
b111 Y
b0 %
b0 H
b0 X
b1000 +
b1000 9
b1000 C
b1000 G
b1000000001110010 0
b1000000001110010 D
b1000000001110010 K
b100 /
b100 L
b100 a
17
#370000
07
#380000
b0 5
b0 <
b0 N
b0 R
b0 S
02
03
b1 *
b1 B
b1 `
b101 &
b101 :
b101 ]
1#
16
04
b0 1
b0 =
b0 A
b0 F
b0 _
b10 !
b10 J
b10 [
b1 $
b1 I
b1 Y
b101 +
b101 9
b101 C
b101 G
b101000000010010 0
b101000000010010 D
b101000000010010 K
b110 /
b110 L
b110 a
17
#390000
07
#400000
1.
06
0#
b0 !
b0 J
b0 [
b0 E
b0 $
b0 I
b0 Y
b1011 +
b1011 9
b1011 C
b1011 G
b1011000000000000 0
b1011000000000000 D
b1011000000000000 K
b111 /
b111 L
b111 a
17
#410000
07
#420000
b1011 5
b1011 <
b1011 N
b1011 R
b1011 S
b101 "
b101 P
b101 Z
b110 '
b110 ;
b110 ?
1,
1-
16
0.
b110 1
b110 =
b110 A
b110 F
b110 _
b110 E
b1 $
b1 I
b1 Y
b1010 +
b1010 9
b1010 C
b1010 G
b1010000000010110 0
b1010000000010110 D
b1010000000010110 K
b0 /
b0 L
b0 a
17
#430000
07
#440000
b101 (
b101 >
b101 T
b101 \
1#
0,
1-
16
b101 !
b101 J
b101 [
b101 %
b101 H
b101 X
b1001 +
b1001 9
b1001 C
b1001 G
b1001010100010110 0
b1001010100010110 D
b1001010100010110 K
b1 /
b1 L
b1 a
17
#450000
07
#460000
b0 5
b0 <
b0 N
b0 R
b0 S
b0 "
b0 P
b0 Z
b101 '
b101 ;
b101 ?
0-
16
1#
b0 1
b0 =
b0 A
b0 F
b0 _
b1000 $
b1000 I
b1000 Y
b0 %
b0 H
b0 X
b101 +
b101 9
b101 C
b101 G
b101000010000101 0
b101000010000101 D
b101000010000101 K
b10 /
b10 L
b10 a
17
#470000
07
#480000
b0 5
b0 <
b0 N
b0 R
b0 S
b0 '
b0 ;
b0 ?
b0 (
b0 >
b0 T
b0 \
16
1#
b111 !
b111 J
b111 [
b101 %
b101 H
b101 X
b110 +
b110 9
b110 C
b110 G
b110010110000111 0
b110010110000111 D
b110010110000111 K
b11 /
b11 L
b11 a
17
#490000
07
#500000
b10 *
b10 B
b10 `
13
12
b101 '
b101 ;
b101 ?
b0 &
b0 :
b0 ]
b101 (
b101 >
b101 T
b101 \
14
16
0#
b10 1
b10 =
b10 A
b10 F
b10 _
b0 !
b0 J
b0 [
b10 E
b111 $
b111 I
b111 Y
b0 %
b0 H
b0 X
b1000 +
b1000 9
b1000 C
b1000 G
b1000000001110010 0
b1000000001110010 D
b1000000001110010 K
b100 /
b100 L
b100 a
17
#510000
07
#520000
b0 5
b0 <
b0 N
b0 R
b0 S
02
03
b1 *
b1 B
b1 `
b101 &
b101 :
b101 ]
1#
16
04
b0 1
b0 =
b0 A
b0 F
b0 _
b10 !
b10 J
b10 [
b1 $
b1 I
b1 Y
b101 +
b101 9
b101 C
b101 G
b101000000010010 0
b101000000010010 D
b101000000010010 K
b110 /
b110 L
b110 a
17
