MUX.v
`timescale 1ns / 1ps
//////////////////////////////////////////////////////////////////////////////////
// Company: 
// Engineer: 
// 
// Create Date: 03/10/2025 02:27:47 AM
// Design Name: 
// Module Name: MUX
// Project Name: 
// Target Devices: 
// Tool Versions: 
// Description: 
// 
// Dependencies: 
// 
// Revision:
// Revision 0.01 - File Created
// Additional Comments:
// 
//////////////////////////////////////////////////////////////////////////////////


module MUX(
    input wire signal,  // Ensure signal is wire (default for inputs)
    input wire [7:0] mux_in1,
    input wire [7:0] mux_in2,
    output reg [7:0] mux_out // Must be 'reg' since it’s assigned in always block
);

initial begin
    mux_out = 8'b0;
end
always @(*) begin
   case(signal)
       1'b0: mux_out = mux_in1;
       1'b1: mux_out = mux_in2;
   endcase
end

endmodule

AND.v
`timescale 1ns / 1ps
//////////////////////////////////////////////////////////////////////////////////
// Company: 
// Engineer: 
// 
// Create Date: 03/10/2025 03:48:42 AM
// Design Name: 
// Module Name: AND
// Project Name: 
// Target Devices: 
// Tool Versions: 
// Description: 
// 
// Dependencies: 
// 
// Revision:
// Revision 0.01 - File Created
// Additional Comments:
// 
//////////////////////////////////////////////////////////////////////////////////


module AND(
input a,
input b,
output c
    );

assign c = a & b;    

endmodule

data_memory.v
`timescale 1ns / 1ps


module data_memory(
input clk,
input [7:0] read_addr,
input [7:0] write_addr,
input [7:0] write_data,
input mem_write,
input mem_enable,
output reg [7:0] read_data
);

reg [7:0] memory [255:0];
integer i;
reg [7:0] register ;

initial begin
   
    for (i = 0; i < 256; i = i + 1)
        memory[i] = 8'b0000_1001; // Default to 9
end

always @(*) begin
    if (mem_enable)
        if (mem_write) 
            memory[write_addr] <= write_data;
        read_data = memory[read_addr];
        register = memory[read_addr];
    // else 
        // read_data = register;
end



endmodule

ALU.v
`timescale 1ns / 1ps

module ALU(
    input wire [7:0] data_in1,
    input wire [7:0] data_in2,
    input wire [3:0] opcode,
    input wire ALU_src,
    input wire clk,
    output reg [7:0] result,
    output reg compare
);

always @(*) begin
    compare <= 1'b0;
    if (ALU_src) begin
        case (opcode)
            4'b0000: result <= data_in1 + data_in2;   // ADD
            4'b0001: result <= data_in1 - data_in2;   // SUB
            4'b0010: result <= data_in1 & data_in2;   // AND
            4'b0011: result <= data_in1 | data_in2;   // OR
            4'b0100: result <= data_in1 ^ data_in2;   // XOR
            4'b0101: compare <= (data_in1 == data_in2) ? 1'b1 : 1'b0; // COMPARE
            4'b0110: result <= data_in1 + data_in2;   // ADD for load
            4'b0111: result <= data_in1 + data_in2;   // ADD for store
            default: result <= 8'b00000000; // Default case (avoid latches)
        endcase
    end
end

endmodule

Register_file.v
`timescale 1ns / 1ps


module Register_file(
input clk,
input [3:0] read_reg1,
input [3:0] read_reg2,
input [3:0] write_reg,
input [7:0] write_data,
input reg_write,
input reg_enable,
output reg [7:0] read_data1,
output reg [7:0] read_data2,
    output [7:0] r4_out,
    output [7:0] r8_out
);

reg [7:0] register_memory [15:0];
reg [7:0] register_1;
reg [7:0] register_2;
integer i;
initial begin
   
    for (i = 0; i < 16; i = i + 1)
        register_memory[i] = 16'b0000_0000_0000_0101; // Default to 5
    //let: r1 = 1,  r2 = 1, r3 = 5, r4 = 0, r5 = 5
    register_memory[1] = 16'b0000_0000_0000_0001; // r1 = 1
    register_memory[2] = 16'b0000_0000_0000_0001; // r2 = 1
    register_memory[3] = 16'b0000_0000_0000_0101; // r3 = 5
    register_memory[4] = 16'b0000_0000_0000_0101; // r4 = 5
    register_memory[5] = 16'b0000_0000_0000_0101; // r5 = 5
    //let r6 = 0, r7 = 1, r8 = 0, r9 = 0 , r10 = 0, r2 = 1, r11 = 5
    register_memory[6] = 16'b0000_0000_0000_0000; // r6 = 0
    register_memory[7] = 16'b0000_0000_0000_0001; // r7 = 1
    register_memory[8] = 16'b0000_0000_0000_0000; // r8 = 0
    register_memory[9] = 16'b0000_0000_0000_0000; // r9 = 0
    register_memory[10] = 16'b0000_0000_0000_0000; // r10 = 0
    register_memory[11] = 16'b0000_0000_0000_0100; // r11 = 4
//    register_memory[0] = 16'b0001_0000_0001_0010; 
end




// Read operation
// always @(*) begin
//     if (reg_enable) begin
//         read_data1 = register_memory[read_reg1];
//         read_data2 = register_memory[read_reg2];
//         register_1 = register_memory[read_reg1];
//         register_2 = register_memory[read_reg2];
//     end else begin
//         read_data1 = register_1;
//         read_data2 = register_2;
//     end
//     if (reg_write & reg_enable) 
//         register_memory[write_reg] <= write_data;
// end

// Combined READ/WRITE operation - combinational
always @(*) begin
    if (reg_enable) begin
        read_data1 = register_memory[read_reg1];
        read_data2 = register_memory[read_reg2];
        register_1 = register_memory[read_reg1];
        register_2 = register_memory[read_reg2];
        
        // Write operation using blocking assignment
        if (reg_write) begin
            register_memory[write_reg] = write_data;
        end
    end else begin
        read_data1 = register_1;
        read_data2 = register_2;
    end
end

assign r4_out = register_memory[4];
assign r8_out = register_memory[8];



endmodule

control_unit_multicycle.v
module control_unit_multicycle(
    input wire clk,              // Clock input
    input wire reset,            // Reset signal
    input wire [4:0] opcode,     // Opcode as input
    output reg reg_write,        // Control signal for Register Write
    output reg branch,
    output reg ALU_src,
    output reg load,
    output reg immediate_signal,
    output reg mem_write,
    output reg jump,
    // New control signals for multi-cycle
    output reg PC_enable,        // Enable signal for program counter
    output reg IR_enable,        // Enable signal for instruction register
    // output reg ALU_enable,       // Enable signal for ALU
    output reg mem_enable,       // Enable signal for memory
    output reg reg_enable        // Enable signal for register file
);

// State definitions
localparam FETCH = 2'b00;
localparam DECODE = 2'b01;
localparam EXECUTE = 2'b10;
localparam MEMORY = 2'b11;
localparam WRITEBACK = 3'b100;  // Needs extra bit

reg [2:0] state, next_state;

// State register
always @(posedge clk or posedge reset) begin
    if (reset)
        state <= FETCH;
    else
        state <= next_state;
end

// always @(posedge reset) begin
//         PC_enable = 1'b1;
// end

// Next state logic
always @(*) begin
    case (state)
        FETCH: next_state = DECODE;
        DECODE: next_state = EXECUTE;
        EXECUTE: begin
            if (opcode == 5'b01001 || opcode == 5'b01010)  // Load or Store
                next_state = MEMORY;
            else if (opcode < 7 || opcode == 5'b01001)    // R-type or Load needs writeback
                next_state = WRITEBACK;
            else                                        // Branch or Jump
                next_state = FETCH;
        end
        MEMORY: begin
            if (opcode == 5'b01001)                      // Load needs writeback
                next_state = WRITEBACK;
            else                                        // Store
                next_state = FETCH;
        end
        WRITEBACK: next_state = FETCH;
        default: next_state = FETCH;
    endcase
end

// Output logic
always @(*) begin
    // Default values
    reg_write = 1'b0;
    branch = 1'b0;
    ALU_src = 1'b0;
    load = 1'b0;
    immediate_signal = 1'b0;
    mem_write = 1'b0;
    jump = 1'b0;
    PC_enable = 1'b0;
    IR_enable = 1'b0;
    // ALU_enable = 1'b0;
    mem_enable = 1'b0;
    reg_enable = 1'b0;
    
    case (state)
        FETCH: begin
            IR_enable = 1'b1;    // Enable instruction register
        end
        
        DECODE: begin
            reg_enable = 1'b1;   // Enable register file for reading
        end
        
        EXECUTE: begin
            // ALU_enable = 1'b1;   // Enable ALU
            if (opcode < 7) begin
                ALU_src = 1'b1;  // R-type
            end
            else if (opcode[4] == 1'b1) begin
                ALU_src = 1'b0;  // I-type
                immediate_signal = 1'b1; 
            end
            else begin
                case (opcode)
                    5'b00111, 5'b01000: begin  // BEQ, BNE
                        ALU_src = 1'b1;
                        branch = 1'b1;
                        PC_enable = 1'b1;    // Update PC for branch
                    end
                    5'b01001, 5'b01010: begin  // Load/Store
                        ALU_src = 1'b1;
                    end
                    5'b01011: begin          // Jump
                        jump = 1'b1;
                        PC_enable = 1'b1;    // Update PC for jump
                    end
                endcase
            end
        end
        
        MEMORY: begin
            mem_enable = 1'b1;   // Enable memory
            if (opcode == 5'b01001) begin  // Load
                load = 1'b1;
                immediate_signal = 1'b1;  
            end
            else if (opcode == 5'b01010) begin  // Store
                mem_write = 1'b1;
                PC_enable = 1'b1;  // Update PC after store completes
            end
        end
        
        WRITEBACK: begin
            reg_enable = 1'b1;    // Enable register file for writing
            reg_write = 1'b1;     // Enable write to register
            PC_enable = 1'b1;     // Update PC after instruction completes
        end
    endcase
end


endmodule

instruction_decoder.v
module instruction_decoder(
    input wire [16:0] instruction,  // Instruction from Instruction Memory
    output reg [4:0] opcode,        // ALU Operation
    output reg [3:0] read_reg1,     // Source Register 1
    output reg [3:0] read_reg2,     // Source Register 2
    output reg [3:0] write_reg,     // Destination Register
    output reg [7:0] immediate      // Immediate Value
);

reg [7:0] extended_value;

always @(*) begin
    opcode    = instruction[16:12]; // Extract opcode (4 bits)
    read_reg1 = instruction[11:8];  // Extract Rs (source register 1)
    read_reg2 = instruction[7:4];   // Extract Rt (source register 2)
    
    if (opcode < 4'b0111) begin // R-type instruction
        write_reg  = instruction[3:0];   // Extract Rd (destination register)
        immediate  = 4'b0000;            // No immediate value in R-type
    end
    //for I-type instructions
    else if (instruction[16] == 1'b1) begin // Check if the instruction is I-type
        write_reg  = instruction[3:0];   // Extract Rd (destination register)
        immediate  = instruction[11:8];           
    end
    else begin
        
        extended_value = {4'b0000, instruction[3:0]}; // Zero-extend to 8 bits
        write_reg  = instruction[11:8];            // No destination register in I-type
        immediate  = extended_value;   // Extract immediate value
        
        // case (opcode)
        //             4'b0101: begin // BEQ
        //                 write_reg  = 4'b0000;            // No destination register in I-type
        //                 immediate  = extended_value;   // Extract immediate value
        //             end
        //             4'b0110: begin // LOAD
        //                 write_reg  = instruction[11:8];            // No destination register in I-type
        //                 immediate  = extended_value;   // Extract immediate value
        //             end
        //             4'b0111: begin // STORE
        //                 write_reg  = instruction[11:8];            // No destination register in I-type
        //                 immediate  = extended_value;   // Extract immediate value
        //             end
        // endcase
    end
end

endmodule

instruction_memory.v
`timescale 1ns / 1ps


module instruction_memory(
input wire [5:0] addr,
output wire [16:0] instruction,
input IR_enable
);

reg [16:0] register_memory [63:0];

assign instruction = register_memory[addr];

integer i;
initial begin
   
    for (i = 0; i < 64; i = i + 1)
        register_memory[i] = 16'b0000_0000_0000_0000; // Default to 0
        //opcode_first_second_destination
        //opcode_first_second_immediate 
        //opcode_first_second_immediate 


    //test program multiplication by 5
    //let: r1 = 1,  r2 = 1, r3 = 5, r4 = 5, r5 = 5
    // 1. ADD r4 r3 r4 // multiplication
    // register_memory[1] = 16'b0000_0100_0011_0100;
    // 2. ADD r1 r2 r1 // increment counter
    // register_memory[2] = 16'b0000_0001_0010_0001;
    // 3. BEQ  r1 r5 0x(5)
    // register_memory[3] = 16'b0111_0001_0101_0010;
    // 4. JUMP 0x(1)
    // register_memory[4] = 16'b1011_0000_0000_0001;
   
    // register_memory[5] = 16'b0000_0100_0000_0000;

    // test program fibbaonacci
    // ADD r6 r7 r8 // r8 = r6 + r7
    register_memory[1] = 16'b0000_0110_0111_1000;
    //ADD r7 r9 r6 // using this add instruction as MOV
    register_memory[2] = 16'b0000_0111_1001_0110;
    //ADD r8 r9 r7 // again moving r8 to r7
    register_memory[3] = 16'b0000_1000_1001_0111;
    //ADD r10 r2 r10 // incrementing r10 
    register_memory[4] = 16'b0000_1010_0010_1010;
    //BEQ r10 r11 0x2 // break the loop (skips 2 instructions)
    register_memory[5] = 16'b0111_1010_1011_0010;
    //  JUMP 0x(1)
    register_memory[6] = 16'b1011_0000_0000_0001;
    register_memory[7] = 16'b0000_1000_0000_0000;

    // register_memory[1] = 16'b1010_0000_0001_0110; // STORE $r0 6($r1) : r1+6 = r0
    // register_memory[1] = 17'b10000_0000_0001_0110; // ADD
    // register_memory[2] = 17'b0000_0110_0001_0111; // ADD
    // register_memory[2] = 17'b1001_0101_0001_0110; // LOAD $r0 6($r1) : r0 = r1+6
    // register_memory[1] = 17'b0100_0000_0001_0110; // XNOR
    // register_memory[2] = 17'b0101_0000_1000_0101;  // shift right
    // register_memory[2] = 17'b0000_0110_1000_0111;  // shift right
    // register_memory[3] = 17'b0110_0101_1000_0111;  // shift left
    // register_memory[4] = 17'b0111_0000_1111_0010;  // branch if equal   
    // register_memory[4] = 17'b1011_0000_0000_0000;  // jump  
    // register_memory[5] = 17'b0101_0000_0001_0000;  
    // register_memory[6] = 17'b0000_0000_0001_0010;
    // register_memory[7] = 17'b1011_0000_0000_0000; // jump to 0 instruction addr 
    //Loop for ever 
    register_memory[16] = 16'b1011_0000_0000_1100;
end





endmodule

program_counter.v
`timescale 1ns / 1ps

module program_counter(
    input clk,
    input rst,               
    input [7:0] pc_increment, // Lower 4 bits of 8-bit input
    input jump, 
    input PC_enable,
    input [7:0] jump_label,
    output reg [5:0] instruction_addr
);

    reg first_cycle; // Flag to track the first cycle after reset

    // Initialize on reset and handle PC updates
    always @(posedge clk or posedge rst) begin
        if (rst) begin
            instruction_addr <= 6'b000000;   // Reset counter
            first_cycle <= 1'b1;          // Set first cycle flag
        end
        else if (first_cycle || PC_enable) begin
            first_cycle <= 1'b0;          // Clear first cycle flag
            
            if (jump)
                instruction_addr <= jump_label[5:0];  // Jump to address
            else if (pc_increment[5:0] == 6'b000000)
                instruction_addr <= instruction_addr + 6'b000001;  // Increment by 1 when pc_increment is 0
            else
                instruction_addr <= instruction_addr + pc_increment[5:0]; // Increment by pc_increment
        end
        // No else case - if !PC_enable and !first_cycle, PC remains unchanged
    end

endmodule

RISC_16_top.v
`timescale 1ns / 1ps

module RISC_16_top(
    input clk,
    input rst,
    output [7:0] r4_out,  // Output for debugging
    output [7:0] r8_out,   // Output for debugging
    output [5:0] instruction_addr
);
    
    // wire [5:0] instruction_addr;
    wire [16:0] instruction;
    
    wire [4:0] opcode;   // ALU Operation
    wire [3:0] read_reg1; // Source Register 1
    wire [3:0] read_reg2; // Source Register 2
    wire [3:0] write_reg; // Destination Register
    wire [7:0] write_data;
    wire [7:0] read_data1;
    wire [7:0] read_data2;
    wire [7:0] immediate;
    wire compare;
    
    //data memory
    wire [7:0] read_data;
    wire mem_write;
    wire load_signal;
    
    // Control signals
    wire reg_write;        // Control signal for Register Write
    wire ALU_src;
    wire branch;
    wire jump;
    wire immediate_signal;
    
    wire branch_increment_signal;
    wire [7:0] pc_increment;
    
    wire [7:0] alu_result;
    wire [7:0] read_data1_mux;
    //enable signals
    wire PC_enable;
    wire reg_enable;
    wire IR_enable;
    wire mem_enable;

    // wire [7:0] r4_out;
    // wire [7:0] r8_out;
    
    // Instantiate the 8-bit counter module
    program_counter uut (
        .clk(clk),
        .rst(rst),
        .instruction_addr(instruction_addr),
        .pc_increment(pc_increment),
        .jump(jump),
        .jump_label(immediate),
        .PC_enable(PC_enable)
    );
    
    instruction_memory im(
      .addr(instruction_addr),
      .instruction(instruction),
      .IR_enable(IR_enable)
    );
    
    instruction_decoder id(
    .opcode(opcode),
    .read_reg1(read_reg1),
    .read_reg2(read_reg2),
    .write_reg(write_reg),
    .instruction(instruction),
    .immediate(immediate)
    );
    
    control_unit_multicycle cu(
    .reset(rst),
    .clk(clk),
    .opcode(opcode),
    .branch(branch),
    .ALU_src(ALU_src),
    .reg_write(reg_write),
    .load(load_signal),
    .mem_write(mem_write),
    .jump(jump),
    .immediate_signal(immediate_signal),
    //enable signals 
    .PC_enable(PC_enable),
    .reg_enable(reg_enable),
    .mem_enable(mem_enable),
    .IR_enable(IR_enable)
    );
    
    Register_file rf(
    .read_reg1(read_reg1),
    .read_reg2(read_reg2),
    .write_reg(write_reg),
    .write_data(write_data),
    .read_data1(read_data1),
    .read_data2(read_data2),
    .reg_write(reg_write),
    .reg_enable(reg_enable),
    // Outputs for debugging
    .r4_out(r4_out),
    .r8_out(r8_out)

    );
    
    ALU alu(
    .data_in1(read_data1_mux),
    .data_in2(read_data2),
    .opcode(opcode),
    .clk(clk),
    .result(alu_result),
    .ALU_src(ALU_src),
    .compare(compare)
    );
    
    data_memory mm(
    .read_addr(alu_result),
    .write_addr(alu_result),
    .write_data(read_data1),
    .mem_write(mem_write),
    .read_data(read_data),
    .mem_enable(mem_enable)
    );
    
    MUX memory_ALU_mux(
    .signal(load_signal),
    .mux_in2(read_data),
    .mux_in1(alu_result),
    .mux_out(write_data)
    );
    
    AND branch_ALU(
    .a(branch),
    .b(compare),
    .c(branch_increment_signal)
    );
    
     MUX alu_input_selector(
    .signal(load_signal),
    .mux_in2(immediate),
    .mux_in1(read_data1),
    .mux_out(read_data1_mux)
    );
    
    MUX branch_mux(
    .signal(branch_increment_signal),
    .mux_in2(immediate),
    .mux_in1(8'b1),
    .mux_out(pc_increment)
    );

endmodule

tb_RISC_16.v
`timescale 1ns / 1ps

module tb_RISC_16;

    // Testbench signals
    reg clk;
    reg rst;
    wire [7:0] r4_out;  // Output for debugging
    wire [7:0] r8_out;  // Output for debugging
    wire [5:0] instruction_addr; // Output for instruction address
    
    // Instantiate the top module
    RISC_16_top uut (
        .clk(clk),
        .rst(rst),
        .r4_out(r4_out),  // Connect output for debugging
        .r8_out(r8_out),   // Connect output for debugging
        .instruction_addr(instruction_addr) // Connect instruction address output
    );

    // Clock generation (10ns period -> 100MHz clock)
    always #10 clk = ~clk;

    initial begin
        // Enable VCD dumping
        $dumpfile("waveform.vcd");  // Name of the output waveform file
        $dumpvars(0, tb_RISC_16);    // Dump all variables in the module
        clk = 0;
        rst = 0;  
        #10 rst = 1; // Release reset after 10ns
        #10 rst = 0;
        
        #10
        clk = ~clk;
        #10
        clk = ~clk;

        #2000;  // Let the simulation run for a longer time
        $finish;  // Stop simulation
    end

    // Monitor changes
    initial begin
        $monitor("Time: %0t | clk: %b | rst: %b | pc_increment: %b | instruction_addr: %b | PC_enable: %b | IR_enable: %b | mem_enable: %b | reg_enable: %b", 
            $time, clk, rst, uut.pc_increment, uut.instruction_addr, uut.PC_enable, uut.IR_enable, uut.mem_enable, uut.reg_enable);
    end

endmodule

waveform.vcd
$date
	Sun Jun 15 22:16:35 2025
$end
$version
	Icarus Verilog
$end
$timescale
	1ps
$end
$scope module tb_RISC_16 $end
$var wire 8 ! r8_out [7:0] $end
$var wire 8 " r4_out [7:0] $end
$var wire 6 # instruction_addr [5:0] $end
$var reg 1 $ clk $end
$var reg 1 % rst $end
$scope module uut $end
$var wire 1 $ clk $end
$var wire 1 % rst $end
$var wire 4 & write_reg [3:0] $end
$var wire 8 ' write_data [7:0] $end
$var wire 1 ( reg_write $end
$var wire 1 ) reg_enable $end
$var wire 4 * read_reg2 [3:0] $end
$var wire 4 + read_reg1 [3:0] $end
$var wire 8 , read_data2 [7:0] $end
$var wire 8 - read_data1_mux [7:0] $end
$var wire 8 . read_data1 [7:0] $end
$var wire 8 / read_data [7:0] $end
$var wire 8 0 r8_out [7:0] $end
$var wire 8 1 r4_out [7:0] $end
$var wire 8 2 pc_increment [7:0] $end
$var wire 5 3 opcode [4:0] $end
$var wire 1 4 mem_write $end
$var wire 1 5 mem_enable $end
$var wire 1 6 load_signal $end
$var wire 1 7 jump $end
$var wire 6 8 instruction_addr [5:0] $end
$var wire 17 9 instruction [16:0] $end
$var wire 1 : immediate_signal $end
$var wire 8 ; immediate [7:0] $end
$var wire 1 < compare $end
$var wire 1 = branch_increment_signal $end
$var wire 1 > branch $end
$var wire 8 ? alu_result [7:0] $end
$var wire 1 @ PC_enable $end
$var wire 1 A IR_enable $end
$var wire 1 B ALU_src $end
$scope module alu $end
$var wire 1 $ clk $end
$var wire 4 C opcode [3:0] $end
$var wire 8 D data_in2 [7:0] $end
$var wire 8 E data_in1 [7:0] $end
$var wire 1 B ALU_src $end
$var reg 1 < compare $end
$var reg 8 F result [7:0] $end
$upscope $end
$scope module alu_input_selector $end
$var wire 1 6 signal $end
$var wire 8 G mux_in2 [7:0] $end
$var wire 8 H mux_in1 [7:0] $end
$var reg 8 I mux_out [7:0] $end
$upscope $end
$scope module branch_ALU $end
$var wire 1 < b $end
$var wire 1 = c $end
$var wire 1 > a $end
$upscope $end
$scope module branch_mux $end
$var wire 8 J mux_in1 [7:0] $end
$var wire 1 = signal $end
$var wire 8 K mux_in2 [7:0] $end
$var reg 8 L mux_out [7:0] $end
$upscope $end
$scope module cu $end
$var wire 1 $ clk $end
$var wire 1 % reset $end
$var wire 5 M opcode [4:0] $end
$var reg 1 B ALU_src $end
$var reg 1 A IR_enable $end
$var reg 1 @ PC_enable $end
$var reg 1 > branch $end
$var reg 1 : immediate_signal $end
$var reg 1 7 jump $end
$var reg 1 6 load $end
$var reg 1 5 mem_enable $end
$var reg 1 4 mem_write $end
$var reg 3 N next_state [2:0] $end
$var reg 1 ) reg_enable $end
$var reg 1 ( reg_write $end
$var reg 3 O state [2:0] $end
$upscope $end
$scope module id $end
$var wire 17 P instruction [16:0] $end
$var reg 8 Q extended_value [7:0] $end
$var reg 8 R immediate [7:0] $end
$var reg 5 S opcode [4:0] $end
$var reg 4 T read_reg1 [3:0] $end
$var reg 4 U read_reg2 [3:0] $end
$var reg 4 V write_reg [3:0] $end
$upscope $end
$scope module im $end
$var wire 1 A IR_enable $end
$var wire 17 W instruction [16:0] $end
$var wire 6 X addr [5:0] $end
$var integer 32 Y i [31:0] $end
$upscope $end
$scope module memory_ALU_mux $end
$var wire 8 Z mux_in1 [7:0] $end
$var wire 1 6 signal $end
$var wire 8 [ mux_in2 [7:0] $end
$var reg 8 \ mux_out [7:0] $end
$upscope $end
$scope module mm $end
$var wire 1 ] clk $end
$var wire 1 5 mem_enable $end
$var wire 1 4 mem_write $end
$var wire 8 ^ read_addr [7:0] $end
$var wire 8 _ write_addr [7:0] $end
$var wire 8 ` write_data [7:0] $end
$var reg 8 a read_data [7:0] $end
$var reg 8 b register [7:0] $end
$var integer 32 c i [31:0] $end
$upscope $end
$scope module rf $end
$var wire 1 d clk $end
$var wire 8 e r4_out [7:0] $end
$var wire 8 f r8_out [7:0] $end
$var wire 4 g read_reg1 [3:0] $end
$var wire 4 h read_reg2 [3:0] $end
$var wire 1 ) reg_enable $end
$var wire 1 ( reg_write $end
$var wire 8 i write_data [7:0] $end
$var wire 4 j write_reg [3:0] $end
$var reg 8 k read_data1 [7:0] $end
$var reg 8 l read_data2 [7:0] $end
$var reg 8 m register_1 [7:0] $end
$var reg 8 n register_2 [7:0] $end
$var integer 32 o i [31:0] $end
$upscope $end
$scope module uut $end
$var wire 1 @ PC_enable $end
$var wire 1 $ clk $end
$var wire 1 7 jump $end
$var wire 8 p jump_label [7:0] $end
$var wire 8 q pc_increment [7:0] $end
$var wire 1 % rst $end
$var reg 1 r first_cycle $end
$var reg 6 s instruction_addr [5:0] $end
$upscope $end
$upscope $end
$upscope $end
$enddefinitions $end
#0
$dumpvars
bx s
xr
b0 q
bx p
b10000 o
bx n
bx m
bx l
bx k
bx j
b0 i
bx h
bx g
b0 f
b101 e
zd
b100000000 c
bx b
bx a
bx `
bx _
bx ^
z]
b0 \
bx [
bx Z
b1000000 Y
bx X
bx W
bx V
bx U
bx T
bx S
bx R
bx Q
bx P
bx O
bx N
bx M
b0 L
bx K
b1 J
b0 I
bx H
bx G
bx F
b0 E
bx D
bx C
xB
xA
x@
bx ?
x>
x=
x<
bx ;
x:
bx 9
bx 8
x7
x6
x5
x4
bx 3
b0 2
b101 1
b0 0
bx /
bx .
b0 -
bx ,
bx +
bx *
x)
x(
b0 '
bx &
0%
0$
bx #
b101 "
b0 !
$end
#10000
b1 2
b1 L
b1 q
b0 C
bx -
bx E
bx I
bx '
bx \
bx i
0=
b0 ;
b0 G
b0 K
b0 R
b0 p
b0 &
b0 V
b0 j
b0 *
b0 U
b0 h
b0 +
b0 T
b0 g
b0 3
b0 M
b0 S
0)
05
1A
0@
07
04
0:
06
0B
0>
0(
b1 N
0<
1r
b0 9
b0 P
b0 W
b0 #
b0 8
b0 X
b0 s
b0 O
1%
1$
#20000
0%
0$
#30000
b0 -
b0 E
b0 I
b1 n
b0 m
b1 ,
b1 D
b1 l
b0 .
b0 H
b0 `
b0 k
1)
0A
b10 N
b1000 &
b1000 V
b1000 j
b111 *
b111 U
b111 h
b110 +
b110 T
b110 g
b1 O
b11001111000 9
b11001111000 P
b11001111000 W
b1 #
b1 8
b1 X
b1 s
0r
0$
#40000
b100 N
1B
0)
b10 O
0$
#50000
b1 !
b1 0
b1 f
b1 '
b1 \
b1 i
b1001 b
b1001 /
b1001 [
b1001 a
1@
1(
1)
0B
b0 N
b1 ?
b1 F
b1 Z
b1 ^
b1 _
b100 O
1$
#60000
0$
#70000
b110 &
b110 V
b110 j
b1001 *
b1001 U
b1001 h
b111 +
b111 T
b111 g
b1 N
1A
0)
0@
0(
b11110010110 9
b11110010110 P
b11110010110 W
b10 #
b10 8
b10 X
b10 s
b0 O
1$
#80000
0$
#90000
b1 -
b1 E
b1 I
b0 n
b1 m
b0 ,
b0 D
b0 l
b1 .
b1 H
b1 `
b1 k
1)
0A
b10 N
b1 O
1$
#100000
0$
#110000
b100 N
1B
0)
b10 O
1$
#120000
0$
#130000
1@
1(
1)
0B
b0 N
b100 O
1$
#140000
0$
#150000
b111 &
b111 V
b111 j
b1000 +
b1000 T
b1000 g
b1 N
1A
0)
0@
0(
b100010010111 9
b100010010111 P
b100010010111 W
b11 #
b11 8
b11 X
b11 s
b0 O
1$
#160000
0$
#170000
1)
0A
b10 N
b1 O
1$
#180000
0$
#190000
b100 N
1B
0)
b10 O
1$
#200000
0$
#210000
1@
1(
1)
0B
b0 N
b100 O
1$
#220000
0$
#230000
b1010 &
b1010 V
b1010 j
b10 *
b10 U
b10 h
b1010 +
b1010 T
b1010 g
b1 N
1A
0)
0@
0(
b101000101010 9
b101000101010 P
b101000101010 W
b100 #
b100 8
b100 X
b100 s
b0 O
1$
#240000
0$
#250000
b0 -
b0 E
b0 I
b1 n
b0 m
b1 ,
b1 D
b1 l
b0 .
b0 H
b0 `
b0 k
1)
0A
b10 N
b1 O
1$
#260000
0$
#270000
b100 N
1B
0)
b10 O
1$
#280000
0$
#290000
1@
1(
1)
0B
b0 N
b100 O
1$
#300000
0$
#310000
b111 C
b10 ;
b10 G
b10 K
b10 R
b10 p
b10 Q
b1011 *
b1011 U
b1011 h
b111 3
b111 M
b111 S
b1 N
1A
0)
0@
0(
b111101010110010 9
b111101010110010 P
b111101010110010 W
b101 #
b101 8
b101 X
b101 s
b0 O
1$
#320000
0$
#330000
b1 -
b1 E
b1 I
b100 n
b1 m
b100 ,
b100 D
b100 l
b1 .
b1 H
b1 `
b1 k
b10 N
1)
0A
b1 O
1$
#340000
0$
#350000
1@
1>
1B
0)
b0 N
b10 O
1$
#360000
0$
#370000
b1011 C
b1 N
1A
0@
0B
0>
b1 ;
b1 G
b1 K
b1 R
b1 p
b0 &
b0 V
b0 j
b1 Q
b0 *
b0 U
b0 h
b0 +
b0 T
b0 g
b1011 3
b1011 M
b1011 S
b0 O
b1011000000000001 9
b1011000000000001 P
b1011000000000001 W
b110 #
b110 8
b110 X
b110 s
1$
#380000
0$
#390000
b101 -
b101 E
b101 I
b101 n
b101 m
b101 ,
b101 D
b101 l
b101 .
b101 H
b101 `
b101 k
1)
0A
b10 N
b1 O
1$
#400000
0$
#410000
b0 N
1@
17
0)
b10 O
1$
#420000
0$
#430000
b0 C
b0 ;
b0 G
b0 K
b0 R
b0 p
b1000 &
b1000 V
b1000 j
b111 *
b111 U
b111 h
b110 +
b110 T
b110 g
b0 3
b0 M
b0 S
1A
0@
07
b1 N
b11001111000 9
b11001111000 P
b11001111000 W
b1 #
b1 8
b1 X
b1 s
b0 O
1$
#440000
0$
#450000
b1 -
b1 E
b1 I
b1 n
b1 m
b1 ,
b1 D
b1 l
b1 .
b1 H
b1 `
b1 k
1)
0A
b10 N
b1 O
1$
#460000
0$
#470000
b100 N
1B
0)
b10 O
1$
#480000
0$
#490000
b10 !
b10 0
b10 f
b10 '
b10 \
b10 i
1@
1(
1)
0B
b0 N
b10 ?
b10 F
b10 Z
b10 ^
b10 _
b100 O
1$
#500000
0$
#510000
b110 &
b110 V
b110 j
b1001 *
b1001 U
b1001 h
b111 +
b111 T
b111 g
b1 N
1A
0)
0@
0(
b11110010110 9
b11110010110 P
b11110010110 W
b10 #
b10 8
b10 X
b10 s
b0 O
1$
#520000
0$
#530000
b0 n
b0 ,
b0 D
b0 l
1)
0A
b10 N
b1 O
1$
#540000
0$
#550000
b100 N
1B
0)
b10 O
1$
#560000
0$
#570000
b1 '
b1 \
b1 i
1@
1(
1)
0B
b0 N
b1 ?
b1 F
b1 Z
b1 ^
b1 _
b100 O
1$
#580000
0$
#590000
b111 &
b111 V
b111 j
b1000 +
b1000 T
b1000 g
b1 N
1A
0)
0@
0(
b100010010111 9
b100010010111 P
b100010010111 W
b11 #
b11 8
b11 X
b11 s
b0 O
1$
#600000
0$
#610000
b10 -
b10 E
b10 I
b10 m
b10 .
b10 H
b10 `
b10 k
1)
0A
b10 N
b1 O
1$
#620000
0$
#630000
b100 N
1B
0)
b10 O
1$
#640000
0$
#650000
b10 '
b10 \
b10 i
1@
1(
1)
0B
b0 N
b10 ?
b10 F
b10 Z
b10 ^
b10 _
b100 O
1$
#660000
0$
#670000
b1010 &
b1010 V
b1010 j
b10 *
b10 U
b10 h
b1010 +
b1010 T
b1010 g
b1 N
1A
0)
0@
0(
b101000101010 9
b101000101010 P
b101000101010 W
b100 #
b100 8
b100 X
b100 s
b0 O
1$
#680000
0$
#690000
b1 -
b1 E
b1 I
b1 n
b1 m
b1 ,
b1 D
b1 l
b1 .
b1 H
b1 `
b1 k
1)
0A
b10 N
b1 O
1$
#700000
0$
#710000
b100 N
1B
0)
b10 O
1$
#720000
0$
#730000
1@
1(
1)
0B
b0 N
b100 O
1$
#740000
0$
#750000
b111 C
b10 ;
b10 G
b10 K
b10 R
b10 p
b10 Q
b1011 *
b1011 U
b1011 h
b111 3
b111 M
b111 S
b1 N
1A
0)
0@
0(
b111101010110010 9
b111101010110010 P
b111101010110010 W
b101 #
b101 8
b101 X
b101 s
b0 O
1$
#760000
0$
